{
  "metadata" : {
    "identifier" : "https://www.nettruyento.com/truyen-tranh/ban-hoc-cua-toi-la-linh-danh-thue-355603",
    "title" : "Bạn Học Của Tôi Là Lính Đánh Thuê - Chapter 39",
    "subtitle" : null,
    "author" : null,
    "narrator" : null,
    "language" : "vi",
    "description" : null,
    "publisher" : "N/A",
    "subject" : null,
    "modified" : null,
    "published" : "2023-05-16",
    "duration" : 0,
    "abridged" : false,
    "conformsTo" : "https://readium.org/webpub-manifest/profiles/divina",
    "numberOfPages" : 137,
    "readingProgression" : "ttb",
    "belongsTo" : null,
    "presentation" : {
      "fit" : "width",
      "overflow" : "scrolled",
      "continuous" : true
    },
    "@type" : null,
    "schema:license" : null
  },
  "links" : [ {
    "rel" : "self",
    "href" : "https://raw.githubusercontent.com/thuvienonline40/book_storage_collection/main/comic_manifest.json",
    "type" : "application/divina+json"
  } ],
  "readingOrder" : [ {
    "href" : "https://raw.githubusercontent.com/tsvhcomic16alt1/comic_storage_two6/main/IMAGE/IMAGE_e05b763660c626dd20185a6da3440385_82c3303b9d2b8ea9d65585fe0ec9934f_05dd972178dcc0d59847de3f0e284018.jpg",
    "type" : "image/jpeg",
    "bitrate" : 0,
    "duration" : 0,
    "title" : null,
    "properties" : null,
    "alternate" : [ {
      "href" : "https://i551.ntcdntempv26.com/data/images/35548/728896/001.jpg?data=net",
      "type" : "image/jpeg",
      "bitrate" : 0,
      "duration" : 0,
      "title" : null,
      "properties" : null,
      "alternate" : null
    } ]
  }, {
    "href" : "https://raw.githubusercontent.com/tsvhcomic16alt1/comic_storage_two6/main/IMAGE/IMAGE_e05b763660c626dd20185a6da3440385_82c3303b9d2b8ea9d65585fe0ec9934f_684cff1c8ce4ed639c66c2e264061ef2.jpg",
    "type" : "image/jpeg",
    "bitrate" : 0,
    "duration" : 0,
    "title" : null,
    "properties" : null,
    "alternate" : [ {
      "href" : "https://i551.ntcdntempv26.com/data/images/35548/728896/002.jpg?data=net",
      "type" : "image/jpeg",
      "bitrate" : 0,
      "duration" : 0,
      "title" : null,
      "properties" : null,
      "alternate" : null
    } ]
  }, {
    "href" : "https://raw.githubusercontent.com/tsvhcomic16alt1/comic_storage_two6/main/IMAGE/IMAGE_e05b763660c626dd20185a6da3440385_82c3303b9d2b8ea9d65585fe0ec9934f_bfe459029f78cd8fabf9bd83c1eddf62.jpg",
    "type" : "image/jpeg",
    "bitrate" : 0,
    "duration" : 0,
    "title" : null,
    "properties" : null,
    "alternate" : [ {
      "href" : "https://i551.ntcdntempv26.com/data/images/35548/728896/003.jpg?data=net",
      "type" : "image/jpeg",
      "bitrate" : 0,
      "duration" : 0,
      "title" : null,
      "properties" : null,
      "alternate" : null
    } ]
  }, {
    "href" : "https://raw.githubusercontent.com/tsvhcomic16alt1/comic_storage_two6/main/IMAGE/IMAGE_e05b763660c626dd20185a6da3440385_82c3303b9d2b8ea9d65585fe0ec9934f_97b7dd3ce25a88f4b63a4d07c0e44b81.jpg",
    "type" : "image/jpeg",
    "bitrate" : 0,
    "duration" : 0,
    "title" : null,
    "properties" : null,
    "alternate" : [ {
      "href" : "https://i551.ntcdntempv26.com/data/images/35548/728896/004.jpg?data=net",
      "type" : "image/jpeg",
      "bitrate" : 0,
      "duration" : 0,
      "title" : null,
      "properties" : null,
      "alternate" : null
    } ]
  }, {
    "href" : "https://raw.githubusercontent.com/tsvhcomic16alt1/comic_storage_two6/main/IMAGE/IMAGE_e05b763660c626dd20185a6da3440385_82c3303b9d2b8ea9d65585fe0ec9934f_e126b6d200bfd95eace7f502844e94ba.jpg",
    "type" : "image/jpeg",
    "bitrate" : 0,
    "duration" : 0,
    "title" : null,
    "properties" : null,
    "alternate" : [ {
      "href" : "https://i551.ntcdntempv26.com/data/images/35548/728896/005.jpg?data=net",
      "type" : "image/jpeg",
      "bitrate" : 0,
      "duration" : 0,
      "title" : null,
      "properties" : null,
      "alternate" : null
    } ]
  }, {
    "href" : "https://raw.githubusercontent.com/tsvhcomic16alt1/comic_storage_two6/main/IMAGE/IMAGE_e05b763660c626dd20185a6da3440385_82c3303b9d2b8ea9d65585fe0ec9934f_e6ed97abe24330ebe892f6512c8488ef.jpg",
    "type" : "image/jpeg",
    "bitrate" : 0,
    "duration" : 0,
    "title" : null,
    "properties" : null,
    "alternate" : [ {
      "href" : "https://i551.ntcdntempv26.com/data/images/35548/728896/006.jpg?data=net",
      "type" : "image/jpeg",
      "bitrate" : 0,
      "duration" : 0,
      "title" : null,
      "properties" : null,
      "alternate" : null
    } ]
  }, {
    "href" : "https://raw.githubusercontent.com/tsvhcomic16alt1/comic_storage_two6/main/IMAGE/IMAGE_e05b763660c626dd20185a6da3440385_82c3303b9d2b8ea9d65585fe0ec9934f_50498ed3b22c1dde66b17133d03e1b2d.jpg",
    "type" : "image/jpeg",
    "bitrate" : 0,
    "duration" : 0,
    "title" : null,
    "properties" : null,
    "alternate" : [ {
      "href" : "https://i551.ntcdntempv26.com/data/images/35548/728896/007.jpg?data=net",
      "type" : "image/jpeg",
      "bitrate" : 0,
      "duration" : 0,
      "title" : null,
      "properties" : null,
      "alternate" : null
    } ]
  }, {
    "href" : "https://raw.githubusercontent.com/tsvhcomic16alt1/comic_storage_two6/main/IMAGE/IMAGE_e05b763660c626dd20185a6da3440385_82c3303b9d2b8ea9d65585fe0ec9934f_5b7fb308e6141ec6ec678ea83ad827c5.jpg",
    "type" : "image/jpeg",
    "bitrate" : 0,
    "duration" : 0,
    "title" : null,
    "properties" : null,
    "alternate" : [ {
      "href" : "https://i551.ntcdntempv26.com/data/images/35548/728896/008.jpg?data=net",
      "type" : "image/jpeg",
      "bitrate" : 0,
      "duration" : 0,
      "title" : null,
      "properties" : null,
      "alternate" : null
    } ]
  }, {
    "href" : "https://raw.githubusercontent.com/tsvhcomic16alt1/comic_storage_two6/main/IMAGE/IMAGE_e05b763660c626dd20185a6da3440385_82c3303b9d2b8ea9d65585fe0ec9934f_e133aecba9e2c318b8d461f83a39474c.jpg",
    "type" : "image/jpeg",
    "bitrate" : 0,
    "duration" : 0,
    "title" : null,
    "properties" : null,
    "alternate" : [ {
      "href" : "https://i551.ntcdntempv26.com/data/images/35548/728896/009.jpg?data=net",
      "type" : "image/jpeg",
      "bitrate" : 0,
      "duration" : 0,
      "title" : null,
      "properties" : null,
      "alternate" : null
    } ]
  }, {
    "href" : "https://raw.githubusercontent.com/tsvhcomic16alt1/comic_storage_two6/main/IMAGE/IMAGE_e05b763660c626dd20185a6da3440385_82c3303b9d2b8ea9d65585fe0ec9934f_4860163a3b9ad74bf6b6dc596e8e35ea.jpg",
    "type" : "image/jpeg",
    "bitrate" : 0,
    "duration" : 0,
    "title" : null,
    "properties" : null,
    "alternate" : [ {
      "href" : "https://i551.ntcdntempv26.com/data/images/35548/728896/010.jpg?data=net",
      "type" : "image/jpeg",
      "bitrate" : 0,
      "duration" : 0,
      "title" : null,
      "properties" : null,
      "alternate" : null
    } ]
  }, {
    "href" : "https://raw.githubusercontent.com/tsvhcomic16alt1/comic_storage_two6/main/IMAGE/IMAGE_e05b763660c626dd20185a6da3440385_82c3303b9d2b8ea9d65585fe0ec9934f_46fdc78e302792bc4501eb4953a484d1.jpg",
    "type" : "image/jpeg",
    "bitrate" : 0,
    "duration" : 0,
    "title" : null,
    "properties" : null,
    "alternate" : [ {
      "href" : "https://i551.ntcdntempv26.com/data/images/35548/728896/011.jpg?data=net",
      "type" : "image/jpeg",
      "bitrate" : 0,
      "duration" : 0,
      "title" : null,
      "properties" : null,
      "alternate" : null
    } ]
  }, {
    "href" : "https://raw.githubusercontent.com/tsvhcomic16alt1/comic_storage_two6/main/IMAGE/IMAGE_e05b763660c626dd20185a6da3440385_82c3303b9d2b8ea9d65585fe0ec9934f_e938130978a42962b268c6541ce38261.jpg",
    "type" : "image/jpeg",
    "bitrate" : 0,
    "duration" : 0,
    "title" : null,
    "properties" : null,
    "alternate" : [ {
      "href" : "https://i551.ntcdntempv26.com/data/images/35548/728896/012.jpg?data=net",
      "type" : "image/jpeg",
      "bitrate" : 0,
      "duration" : 0,
      "title" : null,
      "properties" : null,
      "alternate" : null
    } ]
  }, {
    "href" : "https://raw.githubusercontent.com/tsvhcomic16alt1/comic_storage_two6/main/IMAGE/IMAGE_e05b763660c626dd20185a6da3440385_82c3303b9d2b8ea9d65585fe0ec9934f_10360b8bf92bb8c5749624006048dd9a.jpg",
    "type" : "image/jpeg",
    "bitrate" : 0,
    "duration" : 0,
    "title" : null,
    "properties" : null,
    "alternate" : [ {
      "href" : "https://i551.ntcdntempv26.com/data/images/35548/728896/013.jpg?data=net",
      "type" : "image/jpeg",
      "bitrate" : 0,
      "duration" : 0,
      "title" : null,
      "properties" : null,
      "alternate" : null
    } ]
  }, {
    "href" : "https://raw.githubusercontent.com/tsvhcomic16alt1/comic_storage_two6/main/IMAGE/IMAGE_e05b763660c626dd20185a6da3440385_82c3303b9d2b8ea9d65585fe0ec9934f_b102c16c1a30938d993ca981aab53aed.jpg",
    "type" : "image/jpeg",
    "bitrate" : 0,
    "duration" : 0,
    "title" : null,
    "properties" : null,
    "alternate" : [ {
      "href" : "https://i551.ntcdntempv26.com/data/images/35548/728896/014.jpg?data=net",
      "type" : "image/jpeg",
      "bitrate" : 0,
      "duration" : 0,
      "title" : null,
      "properties" : null,
      "alternate" : null
    } ]
  }, {
    "href" : "https://raw.githubusercontent.com/tsvhcomic16alt1/comic_storage_two6/main/IMAGE/IMAGE_e05b763660c626dd20185a6da3440385_82c3303b9d2b8ea9d65585fe0ec9934f_086a70a0827de518174d6dafc8619762.jpg",
    "type" : "image/jpeg",
    "bitrate" : 0,
    "duration" : 0,
    "title" : null,
    "properties" : null,
    "alternate" : [ {
      "href" : "https://i551.ntcdntempv26.com/data/images/35548/728896/015.jpg?data=net",
      "type" : "image/jpeg",
      "bitrate" : 0,
      "duration" : 0,
      "title" : null,
      "properties" : null,
      "alternate" : null
    } ]
  }, {
    "href" : "https://raw.githubusercontent.com/tsvhcomic16alt1/comic_storage_two6/main/IMAGE/IMAGE_e05b763660c626dd20185a6da3440385_82c3303b9d2b8ea9d65585fe0ec9934f_741f6e4fd7f3060faf7e6b4ad7d266ab.jpg",
    "type" : "image/jpeg",
    "bitrate" : 0,
    "duration" : 0,
    "title" : null,
    "properties" : null,
    "alternate" : [ {
      "href" : "https://i551.ntcdntempv26.com/data/images/35548/728896/016.jpg?data=net",
      "type" : "image/jpeg",
      "bitrate" : 0,
      "duration" : 0,
      "title" : null,
      "properties" : null,
      "alternate" : null
    } ]
  }, {
    "href" : "https://raw.githubusercontent.com/tsvhcomic16alt1/comic_storage_two6/main/IMAGE/IMAGE_e05b763660c626dd20185a6da3440385_82c3303b9d2b8ea9d65585fe0ec9934f_089a55c21f31259834a30817daaca599.jpg",
    "type" : "image/jpeg",
    "bitrate" : 0,
    "duration" : 0,
    "title" : null,
    "properties" : null,
    "alternate" : [ {
      "href" : "https://i551.ntcdntempv26.com/data/images/35548/728896/017.jpg?data=net",
      "type" : "image/jpeg",
      "bitrate" : 0,
      "duration" : 0,
      "title" : null,
      "properties" : null,
      "alternate" : null
    } ]
  }, {
    "href" : "https://raw.githubusercontent.com/tsvhcomic16alt1/comic_storage_two6/main/IMAGE/IMAGE_e05b763660c626dd20185a6da3440385_82c3303b9d2b8ea9d65585fe0ec9934f_4ff536111c0a63a6a4c0ab616d52cf83.jpg",
    "type" : "image/jpeg",
    "bitrate" : 0,
    "duration" : 0,
    "title" : null,
    "properties" : null,
    "alternate" : [ {
      "href" : "https://i551.ntcdntempv26.com/data/images/35548/728896/018.jpg?data=net",
      "type" : "image/jpeg",
      "bitrate" : 0,
      "duration" : 0,
      "title" : null,
      "properties" : null,
      "alternate" : null
    } ]
  }, {
    "href" : "https://raw.githubusercontent.com/tsvhcomic16alt1/comic_storage_two6/main/IMAGE/IMAGE_e05b763660c626dd20185a6da3440385_82c3303b9d2b8ea9d65585fe0ec9934f_e38bf0607590dd236fe88dc7b6c438e7.jpg",
    "type" : "image/jpeg",
    "bitrate" : 0,
    "duration" : 0,
    "title" : null,
    "properties" : null,
    "alternate" : [ {
      "href" : "https://i551.ntcdntempv26.com/data/images/35548/728896/019.jpg?data=net",
      "type" : "image/jpeg",
      "bitrate" : 0,
      "duration" : 0,
      "title" : null,
      "properties" : null,
      "alternate" : null
    } ]
  }, {
    "href" : "https://raw.githubusercontent.com/tsvhcomic16alt1/comic_storage_two6/main/IMAGE/IMAGE_e05b763660c626dd20185a6da3440385_82c3303b9d2b8ea9d65585fe0ec9934f_4c0de77878cb253548e494501a4b8b9b.jpg",
    "type" : "image/jpeg",
    "bitrate" : 0,
    "duration" : 0,
    "title" : null,
    "properties" : null,
    "alternate" : [ {
      "href" : "https://i551.ntcdntempv26.com/data/images/35548/728896/020.jpg?data=net",
      "type" : "image/jpeg",
      "bitrate" : 0,
      "duration" : 0,
      "title" : null,
      "properties" : null,
      "alternate" : null
    } ]
  }, {
    "href" : "https://raw.githubusercontent.com/tsvhcomic16alt1/comic_storage_two6/main/IMAGE/IMAGE_e05b763660c626dd20185a6da3440385_82c3303b9d2b8ea9d65585fe0ec9934f_b13367f34a44b0b835c4e4fe2d52f3ad.jpg",
    "type" : "image/jpeg",
    "bitrate" : 0,
    "duration" : 0,
    "title" : null,
    "properties" : null,
    "alternate" : [ {
      "href" : "https://i551.ntcdntempv26.com/data/images/35548/728896/021.jpg?data=net",
      "type" : "image/jpeg",
      "bitrate" : 0,
      "duration" : 0,
      "title" : null,
      "properties" : null,
      "alternate" : null
    } ]
  }, {
    "href" : "https://raw.githubusercontent.com/tsvhcomic16alt1/comic_storage_two6/main/IMAGE/IMAGE_e05b763660c626dd20185a6da3440385_82c3303b9d2b8ea9d65585fe0ec9934f_9fc3899d4dd8a5c6489fb47ce2262af3.jpg",
    "type" : "image/jpeg",
    "bitrate" : 0,
    "duration" : 0,
    "title" : null,
    "properties" : null,
    "alternate" : [ {
      "href" : "https://i551.ntcdntempv26.com/data/images/35548/728896/022.jpg?data=net",
      "type" : "image/jpeg",
      "bitrate" : 0,
      "duration" : 0,
      "title" : null,
      "properties" : null,
      "alternate" : null
    } ]
  }, {
    "href" : "https://raw.githubusercontent.com/tsvhcomic16alt1/comic_storage_two6/main/IMAGE/IMAGE_e05b763660c626dd20185a6da3440385_82c3303b9d2b8ea9d65585fe0ec9934f_e934739baa29d0d9bf1186b78335d895.jpg",
    "type" : "image/jpeg",
    "bitrate" : 0,
    "duration" : 0,
    "title" : null,
    "properties" : null,
    "alternate" : [ {
      "href" : "https://i551.ntcdntempv26.com/data/images/35548/728896/023.jpg?data=net",
      "type" : "image/jpeg",
      "bitrate" : 0,
      "duration" : 0,
      "title" : null,
      "properties" : null,
      "alternate" : null
    } ]
  }, {
    "href" : "https://raw.githubusercontent.com/tsvhcomic16alt1/comic_storage_two6/main/IMAGE/IMAGE_e05b763660c626dd20185a6da3440385_82c3303b9d2b8ea9d65585fe0ec9934f_cf5f52a3eea10f65bc61a16539234e01.jpg",
    "type" : "image/jpeg",
    "bitrate" : 0,
    "duration" : 0,
    "title" : null,
    "properties" : null,
    "alternate" : [ {
      "href" : "https://i551.ntcdntempv26.com/data/images/35548/728896/024.jpg?data=net",
      "type" : "image/jpeg",
      "bitrate" : 0,
      "duration" : 0,
      "title" : null,
      "properties" : null,
      "alternate" : null
    } ]
  }, {
    "href" : "https://raw.githubusercontent.com/tsvhcomic16alt1/comic_storage_two6/main/IMAGE/IMAGE_e05b763660c626dd20185a6da3440385_82c3303b9d2b8ea9d65585fe0ec9934f_df709b1afcca581473b97bf796413791.jpg",
    "type" : "image/jpeg",
    "bitrate" : 0,
    "duration" : 0,
    "title" : null,
    "properties" : null,
    "alternate" : [ {
      "href" : "https://i551.ntcdntempv26.com/data/images/35548/728896/025.jpg?data=net",
      "type" : "image/jpeg",
      "bitrate" : 0,
      "duration" : 0,
      "title" : null,
      "properties" : null,
      "alternate" : null
    } ]
  }, {
    "href" : "https://raw.githubusercontent.com/tsvhcomic16alt1/comic_storage_two6/main/IMAGE/IMAGE_e05b763660c626dd20185a6da3440385_82c3303b9d2b8ea9d65585fe0ec9934f_afb423a5ce26e68cf29f41f96d9d6869.jpg",
    "type" : "image/jpeg",
    "bitrate" : 0,
    "duration" : 0,
    "title" : null,
    "properties" : null,
    "alternate" : [ {
      "href" : "https://i551.ntcdntempv26.com/data/images/35548/728896/026.jpg?data=net",
      "type" : "image/jpeg",
      "bitrate" : 0,
      "duration" : 0,
      "title" : null,
      "properties" : null,
      "alternate" : null
    } ]
  }, {
    "href" : "https://raw.githubusercontent.com/tsvhcomic16alt1/comic_storage_two6/main/IMAGE/IMAGE_e05b763660c626dd20185a6da3440385_82c3303b9d2b8ea9d65585fe0ec9934f_55195bfe622aa0b2598699798b023437.jpg",
    "type" : "image/jpeg",
    "bitrate" : 0,
    "duration" : 0,
    "title" : null,
    "properties" : null,
    "alternate" : [ {
      "href" : "https://i551.ntcdntempv26.com/data/images/35548/728896/027.jpg?data=net",
      "type" : "image/jpeg",
      "bitrate" : 0,
      "duration" : 0,
      "title" : null,
      "properties" : null,
      "alternate" : null
    } ]
  }, {
    "href" : "https://raw.githubusercontent.com/tsvhcomic16alt1/comic_storage_two6/main/IMAGE/IMAGE_e05b763660c626dd20185a6da3440385_82c3303b9d2b8ea9d65585fe0ec9934f_fd6a47d39f85c50de878c784463b91a7.jpg",
    "type" : "image/jpeg",
    "bitrate" : 0,
    "duration" : 0,
    "title" : null,
    "properties" : null,
    "alternate" : [ {
      "href" : "https://i551.ntcdntempv26.com/data/images/35548/728896/028.jpg?data=net",
      "type" : "image/jpeg",
      "bitrate" : 0,
      "duration" : 0,
      "title" : null,
      "properties" : null,
      "alternate" : null
    } ]
  }, {
    "href" : "https://raw.githubusercontent.com/tsvhcomic16alt1/comic_storage_two6/main/IMAGE/IMAGE_e05b763660c626dd20185a6da3440385_82c3303b9d2b8ea9d65585fe0ec9934f_ef00dbe4832463e689e63a3ce1590b20.jpg",
    "type" : "image/jpeg",
    "bitrate" : 0,
    "duration" : 0,
    "title" : null,
    "properties" : null,
    "alternate" : [ {
      "href" : "https://i551.ntcdntempv26.com/data/images/35548/728896/029.jpg?data=net",
      "type" : "image/jpeg",
      "bitrate" : 0,
      "duration" : 0,
      "title" : null,
      "properties" : null,
      "alternate" : null
    } ]
  }, {
    "href" : "https://raw.githubusercontent.com/tsvhcomic16alt1/comic_storage_two6/main/IMAGE/IMAGE_e05b763660c626dd20185a6da3440385_82c3303b9d2b8ea9d65585fe0ec9934f_4c2a69d7cc595ab568aa200d799d2661.jpg",
    "type" : "image/jpeg",
    "bitrate" : 0,
    "duration" : 0,
    "title" : null,
    "properties" : null,
    "alternate" : [ {
      "href" : "https://i551.ntcdntempv26.com/data/images/35548/728896/030.jpg?data=net",
      "type" : "image/jpeg",
      "bitrate" : 0,
      "duration" : 0,
      "title" : null,
      "properties" : null,
      "alternate" : null
    } ]
  }, {
    "href" : "https://raw.githubusercontent.com/tsvhcomic16alt1/comic_storage_two6/main/IMAGE/IMAGE_e05b763660c626dd20185a6da3440385_82c3303b9d2b8ea9d65585fe0ec9934f_b396acd652ba991d5a3ab16687b823cc.jpg",
    "type" : "image/jpeg",
    "bitrate" : 0,
    "duration" : 0,
    "title" : null,
    "properties" : null,
    "alternate" : [ {
      "href" : "https://i551.ntcdntempv26.com/data/images/35548/728896/031.jpg?data=net",
      "type" : "image/jpeg",
      "bitrate" : 0,
      "duration" : 0,
      "title" : null,
      "properties" : null,
      "alternate" : null
    } ]
  }, {
    "href" : "https://raw.githubusercontent.com/tsvhcomic16alt1/comic_storage_two6/main/IMAGE/IMAGE_e05b763660c626dd20185a6da3440385_82c3303b9d2b8ea9d65585fe0ec9934f_c861163b67c9f37babe68eb672304f44.jpg",
    "type" : "image/jpeg",
    "bitrate" : 0,
    "duration" : 0,
    "title" : null,
    "properties" : null,
    "alternate" : [ {
      "href" : "https://i551.ntcdntempv26.com/data/images/35548/728896/032.jpg?data=net",
      "type" : "image/jpeg",
      "bitrate" : 0,
      "duration" : 0,
      "title" : null,
      "properties" : null,
      "alternate" : null
    } ]
  }, {
    "href" : "https://raw.githubusercontent.com/tsvhcomic16alt1/comic_storage_two6/main/IMAGE/IMAGE_e05b763660c626dd20185a6da3440385_82c3303b9d2b8ea9d65585fe0ec9934f_486e042feb0194228ec539aecf3ba404.jpg",
    "type" : "image/jpeg",
    "bitrate" : 0,
    "duration" : 0,
    "title" : null,
    "properties" : null,
    "alternate" : [ {
      "href" : "https://i551.ntcdntempv26.com/data/images/35548/728896/033.jpg?data=net",
      "type" : "image/jpeg",
      "bitrate" : 0,
      "duration" : 0,
      "title" : null,
      "properties" : null,
      "alternate" : null
    } ]
  }, {
    "href" : "https://raw.githubusercontent.com/tsvhcomic16alt1/comic_storage_two6/main/IMAGE/IMAGE_e05b763660c626dd20185a6da3440385_82c3303b9d2b8ea9d65585fe0ec9934f_509cf276385d55f31d6c2353e5c1f26e.jpg",
    "type" : "image/jpeg",
    "bitrate" : 0,
    "duration" : 0,
    "title" : null,
    "properties" : null,
    "alternate" : [ {
      "href" : "https://i551.ntcdntempv26.com/data/images/35548/728896/034.jpg?data=net",
      "type" : "image/jpeg",
      "bitrate" : 0,
      "duration" : 0,
      "title" : null,
      "properties" : null,
      "alternate" : null
    } ]
  }, {
    "href" : "https://raw.githubusercontent.com/tsvhcomic16alt1/comic_storage_two6/main/IMAGE/IMAGE_e05b763660c626dd20185a6da3440385_82c3303b9d2b8ea9d65585fe0ec9934f_61e93aaa605da55a899daccf8c64c447.jpg",
    "type" : "image/jpeg",
    "bitrate" : 0,
    "duration" : 0,
    "title" : null,
    "properties" : null,
    "alternate" : [ {
      "href" : "https://i551.ntcdntempv26.com/data/images/35548/728896/035.jpg?data=net",
      "type" : "image/jpeg",
      "bitrate" : 0,
      "duration" : 0,
      "title" : null,
      "properties" : null,
      "alternate" : null
    } ]
  }, {
    "href" : "https://raw.githubusercontent.com/tsvhcomic16alt1/comic_storage_two6/main/IMAGE/IMAGE_e05b763660c626dd20185a6da3440385_82c3303b9d2b8ea9d65585fe0ec9934f_82c7da3509acf16bc0e1b81b65956a59.jpg",
    "type" : "image/jpeg",
    "bitrate" : 0,
    "duration" : 0,
    "title" : null,
    "properties" : null,
    "alternate" : [ {
      "href" : "https://i551.ntcdntempv26.com/data/images/35548/728896/036.jpg?data=net",
      "type" : "image/jpeg",
      "bitrate" : 0,
      "duration" : 0,
      "title" : null,
      "properties" : null,
      "alternate" : null
    } ]
  }, {
    "href" : "https://raw.githubusercontent.com/tsvhcomic16alt1/comic_storage_two6/main/IMAGE/IMAGE_e05b763660c626dd20185a6da3440385_82c3303b9d2b8ea9d65585fe0ec9934f_c2cd19f591889dc50dff2a24be4a9765.jpg",
    "type" : "image/jpeg",
    "bitrate" : 0,
    "duration" : 0,
    "title" : null,
    "properties" : null,
    "alternate" : [ {
      "href" : "https://i551.ntcdntempv26.com/data/images/35548/728896/037.jpg?data=net",
      "type" : "image/jpeg",
      "bitrate" : 0,
      "duration" : 0,
      "title" : null,
      "properties" : null,
      "alternate" : null
    } ]
  }, {
    "href" : "https://raw.githubusercontent.com/tsvhcomic16alt1/comic_storage_two6/main/IMAGE/IMAGE_e05b763660c626dd20185a6da3440385_82c3303b9d2b8ea9d65585fe0ec9934f_48896cd5d8af5d1986fe0fdc239d2edc.jpg",
    "type" : "image/jpeg",
    "bitrate" : 0,
    "duration" : 0,
    "title" : null,
    "properties" : null,
    "alternate" : [ {
      "href" : "https://i551.ntcdntempv26.com/data/images/35548/728896/038.jpg?data=net",
      "type" : "image/jpeg",
      "bitrate" : 0,
      "duration" : 0,
      "title" : null,
      "properties" : null,
      "alternate" : null
    } ]
  }, {
    "href" : "https://raw.githubusercontent.com/tsvhcomic16alt1/comic_storage_two6/main/IMAGE/IMAGE_e05b763660c626dd20185a6da3440385_82c3303b9d2b8ea9d65585fe0ec9934f_ddba5ce50ce98e4b0756c140b9617396.jpg",
    "type" : "image/jpeg",
    "bitrate" : 0,
    "duration" : 0,
    "title" : null,
    "properties" : null,
    "alternate" : [ {
      "href" : "https://i551.ntcdntempv26.com/data/images/35548/728896/039.jpg?data=net",
      "type" : "image/jpeg",
      "bitrate" : 0,
      "duration" : 0,
      "title" : null,
      "properties" : null,
      "alternate" : null
    } ]
  }, {
    "href" : "https://raw.githubusercontent.com/tsvhcomic16alt1/comic_storage_two6/main/IMAGE/IMAGE_e05b763660c626dd20185a6da3440385_82c3303b9d2b8ea9d65585fe0ec9934f_c5389231f207282c3fc59f6bc124f96a.jpg",
    "type" : "image/jpeg",
    "bitrate" : 0,
    "duration" : 0,
    "title" : null,
    "properties" : null,
    "alternate" : [ {
      "href" : "https://i551.ntcdntempv26.com/data/images/35548/728896/040.jpg?data=net",
      "type" : "image/jpeg",
      "bitrate" : 0,
      "duration" : 0,
      "title" : null,
      "properties" : null,
      "alternate" : null
    } ]
  }, {
    "href" : "https://raw.githubusercontent.com/tsvhcomic16alt1/comic_storage_two6/main/IMAGE/IMAGE_e05b763660c626dd20185a6da3440385_82c3303b9d2b8ea9d65585fe0ec9934f_631037aec3fb338980b75d943acd5879.jpg",
    "type" : "image/jpeg",
    "bitrate" : 0,
    "duration" : 0,
    "title" : null,
    "properties" : null,
    "alternate" : [ {
      "href" : "https://i551.ntcdntempv26.com/data/images/35548/728896/041.jpg?data=net",
      "type" : "image/jpeg",
      "bitrate" : 0,
      "duration" : 0,
      "title" : null,
      "properties" : null,
      "alternate" : null
    } ]
  }, {
    "href" : "https://raw.githubusercontent.com/tsvhcomic16alt1/comic_storage_two6/main/IMAGE/IMAGE_e05b763660c626dd20185a6da3440385_82c3303b9d2b8ea9d65585fe0ec9934f_c2ee54344ee210f3157a869612fd7c88.jpg",
    "type" : "image/jpeg",
    "bitrate" : 0,
    "duration" : 0,
    "title" : null,
    "properties" : null,
    "alternate" : [ {
      "href" : "https://i551.ntcdntempv26.com/data/images/35548/728896/042.jpg?data=net",
      "type" : "image/jpeg",
      "bitrate" : 0,
      "duration" : 0,
      "title" : null,
      "properties" : null,
      "alternate" : null
    } ]
  }, {
    "href" : "https://raw.githubusercontent.com/tsvhcomic16alt1/comic_storage_two6/main/IMAGE/IMAGE_e05b763660c626dd20185a6da3440385_82c3303b9d2b8ea9d65585fe0ec9934f_2b39abcb531a6ac0e7d65488d9fe621d.jpg",
    "type" : "image/jpeg",
    "bitrate" : 0,
    "duration" : 0,
    "title" : null,
    "properties" : null,
    "alternate" : [ {
      "href" : "https://i551.ntcdntempv26.com/data/images/35548/728896/043.jpg?data=net",
      "type" : "image/jpeg",
      "bitrate" : 0,
      "duration" : 0,
      "title" : null,
      "properties" : null,
      "alternate" : null
    } ]
  }, {
    "href" : "https://raw.githubusercontent.com/tsvhcomic16alt1/comic_storage_two6/main/IMAGE/IMAGE_e05b763660c626dd20185a6da3440385_82c3303b9d2b8ea9d65585fe0ec9934f_3a43f07537df7ad007a98bf4aed704b2.jpg",
    "type" : "image/jpeg",
    "bitrate" : 0,
    "duration" : 0,
    "title" : null,
    "properties" : null,
    "alternate" : [ {
      "href" : "https://i551.ntcdntempv26.com/data/images/35548/728896/044.jpg?data=net",
      "type" : "image/jpeg",
      "bitrate" : 0,
      "duration" : 0,
      "title" : null,
      "properties" : null,
      "alternate" : null
    } ]
  }, {
    "href" : "https://raw.githubusercontent.com/tsvhcomic16alt1/comic_storage_two6/main/IMAGE/IMAGE_e05b763660c626dd20185a6da3440385_82c3303b9d2b8ea9d65585fe0ec9934f_a516720b49426550f808586f7883c120.jpg",
    "type" : "image/jpeg",
    "bitrate" : 0,
    "duration" : 0,
    "title" : null,
    "properties" : null,
    "alternate" : [ {
      "href" : "https://i551.ntcdntempv26.com/data/images/35548/728896/045.jpg?data=net",
      "type" : "image/jpeg",
      "bitrate" : 0,
      "duration" : 0,
      "title" : null,
      "properties" : null,
      "alternate" : null
    } ]
  }, {
    "href" : "https://raw.githubusercontent.com/tsvhcomic16alt1/comic_storage_two6/main/IMAGE/IMAGE_e05b763660c626dd20185a6da3440385_82c3303b9d2b8ea9d65585fe0ec9934f_6f04bb72067a4d0350a3b898c435c512.jpg",
    "type" : "image/jpeg",
    "bitrate" : 0,
    "duration" : 0,
    "title" : null,
    "properties" : null,
    "alternate" : [ {
      "href" : "https://i551.ntcdntempv26.com/data/images/35548/728896/046.jpg?data=net",
      "type" : "image/jpeg",
      "bitrate" : 0,
      "duration" : 0,
      "title" : null,
      "properties" : null,
      "alternate" : null
    } ]
  }, {
    "href" : "https://raw.githubusercontent.com/tsvhcomic16alt1/comic_storage_two6/main/IMAGE/IMAGE_e05b763660c626dd20185a6da3440385_82c3303b9d2b8ea9d65585fe0ec9934f_4d86ae0ba0002ae64d2a241294fea44e.jpg",
    "type" : "image/jpeg",
    "bitrate" : 0,
    "duration" : 0,
    "title" : null,
    "properties" : null,
    "alternate" : [ {
      "href" : "https://i551.ntcdntempv26.com/data/images/35548/728896/047.jpg?data=net",
      "type" : "image/jpeg",
      "bitrate" : 0,
      "duration" : 0,
      "title" : null,
      "properties" : null,
      "alternate" : null
    } ]
  }, {
    "href" : "https://raw.githubusercontent.com/tsvhcomic16alt1/comic_storage_two6/main/IMAGE/IMAGE_e05b763660c626dd20185a6da3440385_82c3303b9d2b8ea9d65585fe0ec9934f_582806cee1c56aaca70a273300a5598f.jpg",
    "type" : "image/jpeg",
    "bitrate" : 0,
    "duration" : 0,
    "title" : null,
    "properties" : null,
    "alternate" : [ {
      "href" : "https://i551.ntcdntempv26.com/data/images/35548/728896/048.jpg?data=net",
      "type" : "image/jpeg",
      "bitrate" : 0,
      "duration" : 0,
      "title" : null,
      "properties" : null,
      "alternate" : null
    } ]
  }, {
    "href" : "https://raw.githubusercontent.com/tsvhcomic16alt1/comic_storage_two6/main/IMAGE/IMAGE_e05b763660c626dd20185a6da3440385_82c3303b9d2b8ea9d65585fe0ec9934f_d6c535bcceb02ca42daa03559fb63ed1.jpg",
    "type" : "image/jpeg",
    "bitrate" : 0,
    "duration" : 0,
    "title" : null,
    "properties" : null,
    "alternate" : [ {
      "href" : "https://i551.ntcdntempv26.com/data/images/35548/728896/049.jpg?data=net",
      "type" : "image/jpeg",
      "bitrate" : 0,
      "duration" : 0,
      "title" : null,
      "properties" : null,
      "alternate" : null
    } ]
  }, {
    "href" : "https://raw.githubusercontent.com/tsvhcomic16alt1/comic_storage_two6/main/IMAGE/IMAGE_e05b763660c626dd20185a6da3440385_82c3303b9d2b8ea9d65585fe0ec9934f_34153ea0d71cdf6d49807981d34f40a4.jpg",
    "type" : "image/jpeg",
    "bitrate" : 0,
    "duration" : 0,
    "title" : null,
    "properties" : null,
    "alternate" : [ {
      "href" : "https://i551.ntcdntempv26.com/data/images/35548/728896/050.jpg?data=net",
      "type" : "image/jpeg",
      "bitrate" : 0,
      "duration" : 0,
      "title" : null,
      "properties" : null,
      "alternate" : null
    } ]
  }, {
    "href" : "https://raw.githubusercontent.com/tsvhcomic16alt1/comic_storage_two6/main/IMAGE/IMAGE_e05b763660c626dd20185a6da3440385_82c3303b9d2b8ea9d65585fe0ec9934f_4a663209769631339b635b2048d1ff06.jpg",
    "type" : "image/jpeg",
    "bitrate" : 0,
    "duration" : 0,
    "title" : null,
    "properties" : null,
    "alternate" : [ {
      "href" : "https://i551.ntcdntempv26.com/data/images/35548/728896/051.jpg?data=net",
      "type" : "image/jpeg",
      "bitrate" : 0,
      "duration" : 0,
      "title" : null,
      "properties" : null,
      "alternate" : null
    } ]
  }, {
    "href" : "https://raw.githubusercontent.com/tsvhcomic16alt1/comic_storage_two6/main/IMAGE/IMAGE_e05b763660c626dd20185a6da3440385_82c3303b9d2b8ea9d65585fe0ec9934f_0abb694ee246bdf409711d27b66601ae.jpg",
    "type" : "image/jpeg",
    "bitrate" : 0,
    "duration" : 0,
    "title" : null,
    "properties" : null,
    "alternate" : [ {
      "href" : "https://i551.ntcdntempv26.com/data/images/35548/728896/052.jpg?data=net",
      "type" : "image/jpeg",
      "bitrate" : 0,
      "duration" : 0,
      "title" : null,
      "properties" : null,
      "alternate" : null
    } ]
  }, {
    "href" : "https://raw.githubusercontent.com/tsvhcomic16alt1/comic_storage_two6/main/IMAGE/IMAGE_e05b763660c626dd20185a6da3440385_82c3303b9d2b8ea9d65585fe0ec9934f_cb90a6942578c86e0964420ef849ea05.jpg",
    "type" : "image/jpeg",
    "bitrate" : 0,
    "duration" : 0,
    "title" : null,
    "properties" : null,
    "alternate" : [ {
      "href" : "https://i551.ntcdntempv26.com/data/images/35548/728896/053.jpg?data=net",
      "type" : "image/jpeg",
      "bitrate" : 0,
      "duration" : 0,
      "title" : null,
      "properties" : null,
      "alternate" : null
    } ]
  }, {
    "href" : "https://raw.githubusercontent.com/tsvhcomic16alt1/comic_storage_two6/main/IMAGE/IMAGE_e05b763660c626dd20185a6da3440385_82c3303b9d2b8ea9d65585fe0ec9934f_9969fbbe2b8186d4ba81f60e0be4d6a9.jpg",
    "type" : "image/jpeg",
    "bitrate" : 0,
    "duration" : 0,
    "title" : null,
    "properties" : null,
    "alternate" : [ {
      "href" : "https://i551.ntcdntempv26.com/data/images/35548/728896/054.jpg?data=net",
      "type" : "image/jpeg",
      "bitrate" : 0,
      "duration" : 0,
      "title" : null,
      "properties" : null,
      "alternate" : null
    } ]
  }, {
    "href" : "https://raw.githubusercontent.com/tsvhcomic16alt1/comic_storage_two6/main/IMAGE/IMAGE_e05b763660c626dd20185a6da3440385_82c3303b9d2b8ea9d65585fe0ec9934f_a02bf3283a7949fcbf3867a8397c5bd9.jpg",
    "type" : "image/jpeg",
    "bitrate" : 0,
    "duration" : 0,
    "title" : null,
    "properties" : null,
    "alternate" : [ {
      "href" : "https://i551.ntcdntempv26.com/data/images/35548/728896/055.jpg?data=net",
      "type" : "image/jpeg",
      "bitrate" : 0,
      "duration" : 0,
      "title" : null,
      "properties" : null,
      "alternate" : null
    } ]
  }, {
    "href" : "https://raw.githubusercontent.com/tsvhcomic16alt1/comic_storage_two6/main/IMAGE/IMAGE_e05b763660c626dd20185a6da3440385_82c3303b9d2b8ea9d65585fe0ec9934f_f7361d41e3b1f923fa512b513b663c59.jpg",
    "type" : "image/jpeg",
    "bitrate" : 0,
    "duration" : 0,
    "title" : null,
    "properties" : null,
    "alternate" : [ {
      "href" : "https://i551.ntcdntempv26.com/data/images/35548/728896/056.jpg?data=net",
      "type" : "image/jpeg",
      "bitrate" : 0,
      "duration" : 0,
      "title" : null,
      "properties" : null,
      "alternate" : null
    } ]
  }, {
    "href" : "https://raw.githubusercontent.com/tsvhcomic16alt1/comic_storage_two6/main/IMAGE/IMAGE_e05b763660c626dd20185a6da3440385_82c3303b9d2b8ea9d65585fe0ec9934f_783c38e75f94bfde6d85f4f093bb2235.jpg",
    "type" : "image/jpeg",
    "bitrate" : 0,
    "duration" : 0,
    "title" : null,
    "properties" : null,
    "alternate" : [ {
      "href" : "https://i551.ntcdntempv26.com/data/images/35548/728896/057.jpg?data=net",
      "type" : "image/jpeg",
      "bitrate" : 0,
      "duration" : 0,
      "title" : null,
      "properties" : null,
      "alternate" : null
    } ]
  }, {
    "href" : "https://raw.githubusercontent.com/tsvhcomic16alt1/comic_storage_two6/main/IMAGE/IMAGE_e05b763660c626dd20185a6da3440385_82c3303b9d2b8ea9d65585fe0ec9934f_eafd41ac5da63eee8c248981b2a24f03.jpg",
    "type" : "image/jpeg",
    "bitrate" : 0,
    "duration" : 0,
    "title" : null,
    "properties" : null,
    "alternate" : [ {
      "href" : "https://i551.ntcdntempv26.com/data/images/35548/728896/058.jpg?data=net",
      "type" : "image/jpeg",
      "bitrate" : 0,
      "duration" : 0,
      "title" : null,
      "properties" : null,
      "alternate" : null
    } ]
  }, {
    "href" : "https://raw.githubusercontent.com/tsvhcomic16alt1/comic_storage_two6/main/IMAGE/IMAGE_e05b763660c626dd20185a6da3440385_82c3303b9d2b8ea9d65585fe0ec9934f_4417329a84e337eecf4ee7b04554614b.jpg",
    "type" : "image/jpeg",
    "bitrate" : 0,
    "duration" : 0,
    "title" : null,
    "properties" : null,
    "alternate" : [ {
      "href" : "https://i551.ntcdntempv26.com/data/images/35548/728896/059.jpg?data=net",
      "type" : "image/jpeg",
      "bitrate" : 0,
      "duration" : 0,
      "title" : null,
      "properties" : null,
      "alternate" : null
    } ]
  }, {
    "href" : "https://raw.githubusercontent.com/tsvhcomic16alt1/comic_storage_two6/main/IMAGE/IMAGE_e05b763660c626dd20185a6da3440385_82c3303b9d2b8ea9d65585fe0ec9934f_9a28ef8963db9ff30f78473ad73ec5fa.jpg",
    "type" : "image/jpeg",
    "bitrate" : 0,
    "duration" : 0,
    "title" : null,
    "properties" : null,
    "alternate" : [ {
      "href" : "https://i551.ntcdntempv26.com/data/images/35548/728896/060.jpg?data=net",
      "type" : "image/jpeg",
      "bitrate" : 0,
      "duration" : 0,
      "title" : null,
      "properties" : null,
      "alternate" : null
    } ]
  }, {
    "href" : "https://raw.githubusercontent.com/tsvhcomic16alt1/comic_storage_two6/main/IMAGE/IMAGE_e05b763660c626dd20185a6da3440385_82c3303b9d2b8ea9d65585fe0ec9934f_beda48cc6c516cdea277efc3cf7c13ae.jpg",
    "type" : "image/jpeg",
    "bitrate" : 0,
    "duration" : 0,
    "title" : null,
    "properties" : null,
    "alternate" : [ {
      "href" : "https://i551.ntcdntempv26.com/data/images/35548/728896/061.jpg?data=net",
      "type" : "image/jpeg",
      "bitrate" : 0,
      "duration" : 0,
      "title" : null,
      "properties" : null,
      "alternate" : null
    } ]
  }, {
    "href" : "https://raw.githubusercontent.com/tsvhcomic16alt1/comic_storage_two6/main/IMAGE/IMAGE_e05b763660c626dd20185a6da3440385_82c3303b9d2b8ea9d65585fe0ec9934f_b0e8f5315acc9a781c98c72658efc578.jpg",
    "type" : "image/jpeg",
    "bitrate" : 0,
    "duration" : 0,
    "title" : null,
    "properties" : null,
    "alternate" : [ {
      "href" : "https://i551.ntcdntempv26.com/data/images/35548/728896/062.jpg?data=net",
      "type" : "image/jpeg",
      "bitrate" : 0,
      "duration" : 0,
      "title" : null,
      "properties" : null,
      "alternate" : null
    } ]
  }, {
    "href" : "https://raw.githubusercontent.com/tsvhcomic16alt1/comic_storage_two6/main/IMAGE/IMAGE_e05b763660c626dd20185a6da3440385_82c3303b9d2b8ea9d65585fe0ec9934f_4c0d2cc46b495e94cceb5fde828d250f.jpg",
    "type" : "image/jpeg",
    "bitrate" : 0,
    "duration" : 0,
    "title" : null,
    "properties" : null,
    "alternate" : [ {
      "href" : "https://i551.ntcdntempv26.com/data/images/35548/728896/063.jpg?data=net",
      "type" : "image/jpeg",
      "bitrate" : 0,
      "duration" : 0,
      "title" : null,
      "properties" : null,
      "alternate" : null
    } ]
  }, {
    "href" : "https://raw.githubusercontent.com/tsvhcomic16alt1/comic_storage_two6/main/IMAGE/IMAGE_e05b763660c626dd20185a6da3440385_82c3303b9d2b8ea9d65585fe0ec9934f_1241aca2e5cb5c3b26fffb07fb314a10.jpg",
    "type" : "image/jpeg",
    "bitrate" : 0,
    "duration" : 0,
    "title" : null,
    "properties" : null,
    "alternate" : [ {
      "href" : "https://i551.ntcdntempv26.com/data/images/35548/728896/064.jpg?data=net",
      "type" : "image/jpeg",
      "bitrate" : 0,
      "duration" : 0,
      "title" : null,
      "properties" : null,
      "alternate" : null
    } ]
  }, {
    "href" : "https://raw.githubusercontent.com/tsvhcomic16alt1/comic_storage_two6/main/IMAGE/IMAGE_e05b763660c626dd20185a6da3440385_82c3303b9d2b8ea9d65585fe0ec9934f_fdb9e1c1a0fcb63f21e69810bcaec572.jpg",
    "type" : "image/jpeg",
    "bitrate" : 0,
    "duration" : 0,
    "title" : null,
    "properties" : null,
    "alternate" : [ {
      "href" : "https://i551.ntcdntempv26.com/data/images/35548/728896/065.jpg?data=net",
      "type" : "image/jpeg",
      "bitrate" : 0,
      "duration" : 0,
      "title" : null,
      "properties" : null,
      "alternate" : null
    } ]
  }, {
    "href" : "https://raw.githubusercontent.com/tsvhcomic16alt1/comic_storage_two6/main/IMAGE/IMAGE_e05b763660c626dd20185a6da3440385_82c3303b9d2b8ea9d65585fe0ec9934f_aad3d30fcd7b440bd9945a2e4785d3f5.jpg",
    "type" : "image/jpeg",
    "bitrate" : 0,
    "duration" : 0,
    "title" : null,
    "properties" : null,
    "alternate" : [ {
      "href" : "https://i551.ntcdntempv26.com/data/images/35548/728896/066.jpg?data=net",
      "type" : "image/jpeg",
      "bitrate" : 0,
      "duration" : 0,
      "title" : null,
      "properties" : null,
      "alternate" : null
    } ]
  }, {
    "href" : "https://raw.githubusercontent.com/tsvhcomic16alt1/comic_storage_two6/main/IMAGE/IMAGE_e05b763660c626dd20185a6da3440385_82c3303b9d2b8ea9d65585fe0ec9934f_41d123d5641064c634be46fdd31002fb.jpg",
    "type" : "image/jpeg",
    "bitrate" : 0,
    "duration" : 0,
    "title" : null,
    "properties" : null,
    "alternate" : [ {
      "href" : "https://i551.ntcdntempv26.com/data/images/35548/728896/067.jpg?data=net",
      "type" : "image/jpeg",
      "bitrate" : 0,
      "duration" : 0,
      "title" : null,
      "properties" : null,
      "alternate" : null
    } ]
  }, {
    "href" : "https://raw.githubusercontent.com/tsvhcomic16alt1/comic_storage_two6/main/IMAGE/IMAGE_e05b763660c626dd20185a6da3440385_82c3303b9d2b8ea9d65585fe0ec9934f_27a9683bd4929f8ee01c03424a791192.jpg",
    "type" : "image/jpeg",
    "bitrate" : 0,
    "duration" : 0,
    "title" : null,
    "properties" : null,
    "alternate" : [ {
      "href" : "https://i551.ntcdntempv26.com/data/images/35548/728896/068.jpg?data=net",
      "type" : "image/jpeg",
      "bitrate" : 0,
      "duration" : 0,
      "title" : null,
      "properties" : null,
      "alternate" : null
    } ]
  }, {
    "href" : "https://raw.githubusercontent.com/tsvhcomic16alt1/comic_storage_two6/main/IMAGE/IMAGE_e05b763660c626dd20185a6da3440385_82c3303b9d2b8ea9d65585fe0ec9934f_80d91436dca5b9d4f5ab267d972419a9.jpg",
    "type" : "image/jpeg",
    "bitrate" : 0,
    "duration" : 0,
    "title" : null,
    "properties" : null,
    "alternate" : [ {
      "href" : "https://i551.ntcdntempv26.com/data/images/35548/728896/069.jpg?data=net",
      "type" : "image/jpeg",
      "bitrate" : 0,
      "duration" : 0,
      "title" : null,
      "properties" : null,
      "alternate" : null
    } ]
  }, {
    "href" : "https://raw.githubusercontent.com/tsvhcomic16alt1/comic_storage_two6/main/IMAGE/IMAGE_e05b763660c626dd20185a6da3440385_82c3303b9d2b8ea9d65585fe0ec9934f_e5f400aaf856eff45219cacf43713d58.jpg",
    "type" : "image/jpeg",
    "bitrate" : 0,
    "duration" : 0,
    "title" : null,
    "properties" : null,
    "alternate" : [ {
      "href" : "https://i551.ntcdntempv26.com/data/images/35548/728896/070.jpg?data=net",
      "type" : "image/jpeg",
      "bitrate" : 0,
      "duration" : 0,
      "title" : null,
      "properties" : null,
      "alternate" : null
    } ]
  }, {
    "href" : "https://raw.githubusercontent.com/tsvhcomic16alt1/comic_storage_two6/main/IMAGE/IMAGE_e05b763660c626dd20185a6da3440385_82c3303b9d2b8ea9d65585fe0ec9934f_a66ed3ce5dd6786204b3cdef6f8f31a6.jpg",
    "type" : "image/jpeg",
    "bitrate" : 0,
    "duration" : 0,
    "title" : null,
    "properties" : null,
    "alternate" : [ {
      "href" : "https://i551.ntcdntempv26.com/data/images/35548/728896/071.jpg?data=net",
      "type" : "image/jpeg",
      "bitrate" : 0,
      "duration" : 0,
      "title" : null,
      "properties" : null,
      "alternate" : null
    } ]
  }, {
    "href" : "https://raw.githubusercontent.com/tsvhcomic16alt1/comic_storage_two6/main/IMAGE/IMAGE_e05b763660c626dd20185a6da3440385_82c3303b9d2b8ea9d65585fe0ec9934f_01c89e9521c405ab87bc1f5ede51c2b1.jpg",
    "type" : "image/jpeg",
    "bitrate" : 0,
    "duration" : 0,
    "title" : null,
    "properties" : null,
    "alternate" : [ {
      "href" : "https://i551.ntcdntempv26.com/data/images/35548/728896/072.jpg?data=net",
      "type" : "image/jpeg",
      "bitrate" : 0,
      "duration" : 0,
      "title" : null,
      "properties" : null,
      "alternate" : null
    } ]
  }, {
    "href" : "https://raw.githubusercontent.com/tsvhcomic16alt1/comic_storage_two6/main/IMAGE/IMAGE_e05b763660c626dd20185a6da3440385_82c3303b9d2b8ea9d65585fe0ec9934f_86dcd15d2f88574323a2d0d8ef5c179c.jpg",
    "type" : "image/jpeg",
    "bitrate" : 0,
    "duration" : 0,
    "title" : null,
    "properties" : null,
    "alternate" : [ {
      "href" : "https://i551.ntcdntempv26.com/data/images/35548/728896/073.jpg?data=net",
      "type" : "image/jpeg",
      "bitrate" : 0,
      "duration" : 0,
      "title" : null,
      "properties" : null,
      "alternate" : null
    } ]
  }, {
    "href" : "https://raw.githubusercontent.com/tsvhcomic16alt1/comic_storage_two6/main/IMAGE/IMAGE_e05b763660c626dd20185a6da3440385_82c3303b9d2b8ea9d65585fe0ec9934f_b2246b09da7bcd551b0135af2eca89f5.jpg",
    "type" : "image/jpeg",
    "bitrate" : 0,
    "duration" : 0,
    "title" : null,
    "properties" : null,
    "alternate" : [ {
      "href" : "https://i551.ntcdntempv26.com/data/images/35548/728896/074.jpg?data=net",
      "type" : "image/jpeg",
      "bitrate" : 0,
      "duration" : 0,
      "title" : null,
      "properties" : null,
      "alternate" : null
    } ]
  }, {
    "href" : "https://raw.githubusercontent.com/tsvhcomic16alt1/comic_storage_two6/main/IMAGE/IMAGE_e05b763660c626dd20185a6da3440385_82c3303b9d2b8ea9d65585fe0ec9934f_6bd7e04f4212b00136396c38cf537eec.jpg",
    "type" : "image/jpeg",
    "bitrate" : 0,
    "duration" : 0,
    "title" : null,
    "properties" : null,
    "alternate" : [ {
      "href" : "https://i551.ntcdntempv26.com/data/images/35548/728896/075.jpg?data=net",
      "type" : "image/jpeg",
      "bitrate" : 0,
      "duration" : 0,
      "title" : null,
      "properties" : null,
      "alternate" : null
    } ]
  }, {
    "href" : "https://raw.githubusercontent.com/tsvhcomic16alt1/comic_storage_two6/main/IMAGE/IMAGE_e05b763660c626dd20185a6da3440385_82c3303b9d2b8ea9d65585fe0ec9934f_f3af0c2be140f1c205e2ba585181d6ec.jpg",
    "type" : "image/jpeg",
    "bitrate" : 0,
    "duration" : 0,
    "title" : null,
    "properties" : null,
    "alternate" : [ {
      "href" : "https://i551.ntcdntempv26.com/data/images/35548/728896/076.jpg?data=net",
      "type" : "image/jpeg",
      "bitrate" : 0,
      "duration" : 0,
      "title" : null,
      "properties" : null,
      "alternate" : null
    } ]
  }, {
    "href" : "https://raw.githubusercontent.com/tsvhcomic16alt1/comic_storage_two6/main/IMAGE/IMAGE_e05b763660c626dd20185a6da3440385_82c3303b9d2b8ea9d65585fe0ec9934f_23476c9e34ef44121b39bc8bfa3d3418.jpg",
    "type" : "image/jpeg",
    "bitrate" : 0,
    "duration" : 0,
    "title" : null,
    "properties" : null,
    "alternate" : [ {
      "href" : "https://i551.ntcdntempv26.com/data/images/35548/728896/077.jpg?data=net",
      "type" : "image/jpeg",
      "bitrate" : 0,
      "duration" : 0,
      "title" : null,
      "properties" : null,
      "alternate" : null
    } ]
  }, {
    "href" : "https://raw.githubusercontent.com/tsvhcomic16alt1/comic_storage_two6/main/IMAGE/IMAGE_e05b763660c626dd20185a6da3440385_82c3303b9d2b8ea9d65585fe0ec9934f_990d9ba1104ad3bbe19bdf993200b87f.jpg",
    "type" : "image/jpeg",
    "bitrate" : 0,
    "duration" : 0,
    "title" : null,
    "properties" : null,
    "alternate" : [ {
      "href" : "https://i551.ntcdntempv26.com/data/images/35548/728896/078.jpg?data=net",
      "type" : "image/jpeg",
      "bitrate" : 0,
      "duration" : 0,
      "title" : null,
      "properties" : null,
      "alternate" : null
    } ]
  }, {
    "href" : "https://raw.githubusercontent.com/tsvhcomic16alt1/comic_storage_two6/main/IMAGE/IMAGE_e05b763660c626dd20185a6da3440385_82c3303b9d2b8ea9d65585fe0ec9934f_a6f5e23dc1506a6786352b587ea74232.jpg",
    "type" : "image/jpeg",
    "bitrate" : 0,
    "duration" : 0,
    "title" : null,
    "properties" : null,
    "alternate" : [ {
      "href" : "https://i551.ntcdntempv26.com/data/images/35548/728896/079.jpg?data=net",
      "type" : "image/jpeg",
      "bitrate" : 0,
      "duration" : 0,
      "title" : null,
      "properties" : null,
      "alternate" : null
    } ]
  }, {
    "href" : "https://raw.githubusercontent.com/tsvhcomic16alt1/comic_storage_two6/main/IMAGE/IMAGE_e05b763660c626dd20185a6da3440385_82c3303b9d2b8ea9d65585fe0ec9934f_85f83ff1c16cfad0e77a4848bee1bfe6.jpg",
    "type" : "image/jpeg",
    "bitrate" : 0,
    "duration" : 0,
    "title" : null,
    "properties" : null,
    "alternate" : [ {
      "href" : "https://i551.ntcdntempv26.com/data/images/35548/728896/080.jpg?data=net",
      "type" : "image/jpeg",
      "bitrate" : 0,
      "duration" : 0,
      "title" : null,
      "properties" : null,
      "alternate" : null
    } ]
  }, {
    "href" : "https://raw.githubusercontent.com/tsvhcomic16alt1/comic_storage_two6/main/IMAGE/IMAGE_e05b763660c626dd20185a6da3440385_82c3303b9d2b8ea9d65585fe0ec9934f_71e7fc13e6819b265101561ad4f37988.jpg",
    "type" : "image/jpeg",
    "bitrate" : 0,
    "duration" : 0,
    "title" : null,
    "properties" : null,
    "alternate" : [ {
      "href" : "https://i551.ntcdntempv26.com/data/images/35548/728896/081.jpg?data=net",
      "type" : "image/jpeg",
      "bitrate" : 0,
      "duration" : 0,
      "title" : null,
      "properties" : null,
      "alternate" : null
    } ]
  }, {
    "href" : "https://raw.githubusercontent.com/tsvhcomic16alt1/comic_storage_two6/main/IMAGE/IMAGE_e05b763660c626dd20185a6da3440385_82c3303b9d2b8ea9d65585fe0ec9934f_0aa4e0d420c8d52412caef8f27c8cd1f.jpg",
    "type" : "image/jpeg",
    "bitrate" : 0,
    "duration" : 0,
    "title" : null,
    "properties" : null,
    "alternate" : [ {
      "href" : "https://i551.ntcdntempv26.com/data/images/35548/728896/082.jpg?data=net",
      "type" : "image/jpeg",
      "bitrate" : 0,
      "duration" : 0,
      "title" : null,
      "properties" : null,
      "alternate" : null
    } ]
  }, {
    "href" : "https://raw.githubusercontent.com/tsvhcomic16alt1/comic_storage_two6/main/IMAGE/IMAGE_e05b763660c626dd20185a6da3440385_82c3303b9d2b8ea9d65585fe0ec9934f_2b6764d4a02af7585e6110a88d801199.jpg",
    "type" : "image/jpeg",
    "bitrate" : 0,
    "duration" : 0,
    "title" : null,
    "properties" : null,
    "alternate" : [ {
      "href" : "https://i551.ntcdntempv26.com/data/images/35548/728896/083.jpg?data=net",
      "type" : "image/jpeg",
      "bitrate" : 0,
      "duration" : 0,
      "title" : null,
      "properties" : null,
      "alternate" : null
    } ]
  }, {
    "href" : "https://raw.githubusercontent.com/tsvhcomic16alt1/comic_storage_two6/main/IMAGE/IMAGE_e05b763660c626dd20185a6da3440385_82c3303b9d2b8ea9d65585fe0ec9934f_23e4ad0388b5de906faa6925dfbab25e.jpg",
    "type" : "image/jpeg",
    "bitrate" : 0,
    "duration" : 0,
    "title" : null,
    "properties" : null,
    "alternate" : [ {
      "href" : "https://i551.ntcdntempv26.com/data/images/35548/728896/084.jpg?data=net",
      "type" : "image/jpeg",
      "bitrate" : 0,
      "duration" : 0,
      "title" : null,
      "properties" : null,
      "alternate" : null
    } ]
  }, {
    "href" : "https://raw.githubusercontent.com/tsvhcomic16alt1/comic_storage_two6/main/IMAGE/IMAGE_e05b763660c626dd20185a6da3440385_82c3303b9d2b8ea9d65585fe0ec9934f_8223761032f888340412c6d9233e0855.jpg",
    "type" : "image/jpeg",
    "bitrate" : 0,
    "duration" : 0,
    "title" : null,
    "properties" : null,
    "alternate" : [ {
      "href" : "https://i551.ntcdntempv26.com/data/images/35548/728896/085.jpg?data=net",
      "type" : "image/jpeg",
      "bitrate" : 0,
      "duration" : 0,
      "title" : null,
      "properties" : null,
      "alternate" : null
    } ]
  }, {
    "href" : "https://raw.githubusercontent.com/tsvhcomic16alt1/comic_storage_two6/main/IMAGE/IMAGE_e05b763660c626dd20185a6da3440385_82c3303b9d2b8ea9d65585fe0ec9934f_e1ade4c377c4394fbe2475a8219e7168.jpg",
    "type" : "image/jpeg",
    "bitrate" : 0,
    "duration" : 0,
    "title" : null,
    "properties" : null,
    "alternate" : [ {
      "href" : "https://i551.ntcdntempv26.com/data/images/35548/728896/086.jpg?data=net",
      "type" : "image/jpeg",
      "bitrate" : 0,
      "duration" : 0,
      "title" : null,
      "properties" : null,
      "alternate" : null
    } ]
  }, {
    "href" : "https://raw.githubusercontent.com/tsvhcomic16alt1/comic_storage_two6/main/IMAGE/IMAGE_e05b763660c626dd20185a6da3440385_82c3303b9d2b8ea9d65585fe0ec9934f_95b1c9c0891229fc2e4a15991a9a405c.jpg",
    "type" : "image/jpeg",
    "bitrate" : 0,
    "duration" : 0,
    "title" : null,
    "properties" : null,
    "alternate" : [ {
      "href" : "https://i551.ntcdntempv26.com/data/images/35548/728896/087.jpg?data=net",
      "type" : "image/jpeg",
      "bitrate" : 0,
      "duration" : 0,
      "title" : null,
      "properties" : null,
      "alternate" : null
    } ]
  }, {
    "href" : "https://raw.githubusercontent.com/tsvhcomic16alt1/comic_storage_two6/main/IMAGE/IMAGE_e05b763660c626dd20185a6da3440385_82c3303b9d2b8ea9d65585fe0ec9934f_6f40d342e5487314dfb9fd5c64041e2a.jpg",
    "type" : "image/jpeg",
    "bitrate" : 0,
    "duration" : 0,
    "title" : null,
    "properties" : null,
    "alternate" : [ {
      "href" : "https://i551.ntcdntempv26.com/data/images/35548/728896/088.jpg?data=net",
      "type" : "image/jpeg",
      "bitrate" : 0,
      "duration" : 0,
      "title" : null,
      "properties" : null,
      "alternate" : null
    } ]
  }, {
    "href" : "https://raw.githubusercontent.com/tsvhcomic16alt1/comic_storage_two6/main/IMAGE/IMAGE_e05b763660c626dd20185a6da3440385_82c3303b9d2b8ea9d65585fe0ec9934f_b83a24481a59e701063ed0dc26eb6061.jpg",
    "type" : "image/jpeg",
    "bitrate" : 0,
    "duration" : 0,
    "title" : null,
    "properties" : null,
    "alternate" : [ {
      "href" : "https://i551.ntcdntempv26.com/data/images/35548/728896/089.jpg?data=net",
      "type" : "image/jpeg",
      "bitrate" : 0,
      "duration" : 0,
      "title" : null,
      "properties" : null,
      "alternate" : null
    } ]
  }, {
    "href" : "https://raw.githubusercontent.com/tsvhcomic16alt1/comic_storage_two6/main/IMAGE/IMAGE_e05b763660c626dd20185a6da3440385_82c3303b9d2b8ea9d65585fe0ec9934f_fd111497a9f878c01c1584c6277cc9d9.jpg",
    "type" : "image/jpeg",
    "bitrate" : 0,
    "duration" : 0,
    "title" : null,
    "properties" : null,
    "alternate" : [ {
      "href" : "https://i551.ntcdntempv26.com/data/images/35548/728896/090.jpg?data=net",
      "type" : "image/jpeg",
      "bitrate" : 0,
      "duration" : 0,
      "title" : null,
      "properties" : null,
      "alternate" : null
    } ]
  }, {
    "href" : "https://raw.githubusercontent.com/tsvhcomic16alt1/comic_storage_two6/main/IMAGE/IMAGE_e05b763660c626dd20185a6da3440385_82c3303b9d2b8ea9d65585fe0ec9934f_9718d473ff71da859dfd1b503689097a.jpg",
    "type" : "image/jpeg",
    "bitrate" : 0,
    "duration" : 0,
    "title" : null,
    "properties" : null,
    "alternate" : [ {
      "href" : "https://i551.ntcdntempv26.com/data/images/35548/728896/091.jpg?data=net",
      "type" : "image/jpeg",
      "bitrate" : 0,
      "duration" : 0,
      "title" : null,
      "properties" : null,
      "alternate" : null
    } ]
  }, {
    "href" : "https://raw.githubusercontent.com/tsvhcomic16alt1/comic_storage_two6/main/IMAGE/IMAGE_e05b763660c626dd20185a6da3440385_82c3303b9d2b8ea9d65585fe0ec9934f_b0e01f17cd081468069dd62798f5ec6f.jpg",
    "type" : "image/jpeg",
    "bitrate" : 0,
    "duration" : 0,
    "title" : null,
    "properties" : null,
    "alternate" : [ {
      "href" : "https://i551.ntcdntempv26.com/data/images/35548/728896/092.jpg?data=net",
      "type" : "image/jpeg",
      "bitrate" : 0,
      "duration" : 0,
      "title" : null,
      "properties" : null,
      "alternate" : null
    } ]
  }, {
    "href" : "https://raw.githubusercontent.com/tsvhcomic16alt1/comic_storage_two6/main/IMAGE/IMAGE_e05b763660c626dd20185a6da3440385_82c3303b9d2b8ea9d65585fe0ec9934f_d0ae4a58ae57b9491cd392ed1ecffbd2.jpg",
    "type" : "image/jpeg",
    "bitrate" : 0,
    "duration" : 0,
    "title" : null,
    "properties" : null,
    "alternate" : [ {
      "href" : "https://i551.ntcdntempv26.com/data/images/35548/728896/093.jpg?data=net",
      "type" : "image/jpeg",
      "bitrate" : 0,
      "duration" : 0,
      "title" : null,
      "properties" : null,
      "alternate" : null
    } ]
  }, {
    "href" : "https://raw.githubusercontent.com/tsvhcomic16alt1/comic_storage_two6/main/IMAGE/IMAGE_e05b763660c626dd20185a6da3440385_82c3303b9d2b8ea9d65585fe0ec9934f_0cba069b1420a84e5183ea3faa19cb56.jpg",
    "type" : "image/jpeg",
    "bitrate" : 0,
    "duration" : 0,
    "title" : null,
    "properties" : null,
    "alternate" : [ {
      "href" : "https://i551.ntcdntempv26.com/data/images/35548/728896/094.jpg?data=net",
      "type" : "image/jpeg",
      "bitrate" : 0,
      "duration" : 0,
      "title" : null,
      "properties" : null,
      "alternate" : null
    } ]
  }, {
    "href" : "https://raw.githubusercontent.com/tsvhcomic16alt1/comic_storage_two6/main/IMAGE/IMAGE_e05b763660c626dd20185a6da3440385_82c3303b9d2b8ea9d65585fe0ec9934f_e4593f7293b97849767aee44d0f6d8dd.jpg",
    "type" : "image/jpeg",
    "bitrate" : 0,
    "duration" : 0,
    "title" : null,
    "properties" : null,
    "alternate" : [ {
      "href" : "https://i551.ntcdntempv26.com/data/images/35548/728896/095.jpg?data=net",
      "type" : "image/jpeg",
      "bitrate" : 0,
      "duration" : 0,
      "title" : null,
      "properties" : null,
      "alternate" : null
    } ]
  }, {
    "href" : "https://raw.githubusercontent.com/tsvhcomic16alt1/comic_storage_two6/main/IMAGE/IMAGE_e05b763660c626dd20185a6da3440385_82c3303b9d2b8ea9d65585fe0ec9934f_45a7b81dabd243cecf95edd8c519d345.jpg",
    "type" : "image/jpeg",
    "bitrate" : 0,
    "duration" : 0,
    "title" : null,
    "properties" : null,
    "alternate" : [ {
      "href" : "https://i551.ntcdntempv26.com/data/images/35548/728896/096.jpg?data=net",
      "type" : "image/jpeg",
      "bitrate" : 0,
      "duration" : 0,
      "title" : null,
      "properties" : null,
      "alternate" : null
    } ]
  }, {
    "href" : "https://raw.githubusercontent.com/tsvhcomic16alt1/comic_storage_two6/main/IMAGE/IMAGE_e05b763660c626dd20185a6da3440385_82c3303b9d2b8ea9d65585fe0ec9934f_896ca893c04283b0d4d0605a258a8468.jpg",
    "type" : "image/jpeg",
    "bitrate" : 0,
    "duration" : 0,
    "title" : null,
    "properties" : null,
    "alternate" : [ {
      "href" : "https://i551.ntcdntempv26.com/data/images/35548/728896/097.jpg?data=net",
      "type" : "image/jpeg",
      "bitrate" : 0,
      "duration" : 0,
      "title" : null,
      "properties" : null,
      "alternate" : null
    } ]
  }, {
    "href" : "https://raw.githubusercontent.com/tsvhcomic16alt1/comic_storage_two6/main/IMAGE/IMAGE_e05b763660c626dd20185a6da3440385_82c3303b9d2b8ea9d65585fe0ec9934f_d701abade1ea165fa288287b73aa9c96.jpg",
    "type" : "image/jpeg",
    "bitrate" : 0,
    "duration" : 0,
    "title" : null,
    "properties" : null,
    "alternate" : [ {
      "href" : "https://i551.ntcdntempv26.com/data/images/35548/728896/098.jpg?data=net",
      "type" : "image/jpeg",
      "bitrate" : 0,
      "duration" : 0,
      "title" : null,
      "properties" : null,
      "alternate" : null
    } ]
  }, {
    "href" : "https://raw.githubusercontent.com/tsvhcomic16alt1/comic_storage_two6/main/IMAGE/IMAGE_e05b763660c626dd20185a6da3440385_82c3303b9d2b8ea9d65585fe0ec9934f_e5d2bcc21dc009fd34aa3f3ca9e0942c.jpg",
    "type" : "image/jpeg",
    "bitrate" : 0,
    "duration" : 0,
    "title" : null,
    "properties" : null,
    "alternate" : [ {
      "href" : "https://i551.ntcdntempv26.com/data/images/35548/728896/099.jpg?data=net",
      "type" : "image/jpeg",
      "bitrate" : 0,
      "duration" : 0,
      "title" : null,
      "properties" : null,
      "alternate" : null
    } ]
  }, {
    "href" : "https://raw.githubusercontent.com/tsvhcomic16alt1/comic_storage_two6/main/IMAGE/IMAGE_e05b763660c626dd20185a6da3440385_82c3303b9d2b8ea9d65585fe0ec9934f_5e5d39bb19ccfda6fd948417a1e0872d.jpg",
    "type" : "image/jpeg",
    "bitrate" : 0,
    "duration" : 0,
    "title" : null,
    "properties" : null,
    "alternate" : [ {
      "href" : "https://i551.ntcdntempv26.com/data/images/35548/728896/100.jpg?data=net",
      "type" : "image/jpeg",
      "bitrate" : 0,
      "duration" : 0,
      "title" : null,
      "properties" : null,
      "alternate" : null
    } ]
  } ],
  "toc" : null,
  "@context" : "https://readium.org/webpub-manifest/context.jsonld"
}