{
  "metadata" : {
    "identifier" : "https://nghetruyenma.net/oan-hon-bi-phong-an.html",
    "title" : "Oan Hồn Bị Phong Ấn",
    "subtitle" : "N/A",
    "author" : {
      "name" : "Khả Hân",
      "sortAs" : ""
    },
    "narrator" : "N/A",
    "language" : "vi",
    "description" : "N/A",
    "publisher" : "N/A",
    "subject" : null,
    "modified" : null,
    "published" : "2023-06-26",
    "duration" : 3902,
    "abridged" : false,
    "conformsTo" : null,
    "numberOfPages" : null,
    "readingProgression" : null,
    "belongsTo" : null,
    "presentation" : null,
    "@type" : "http://schema.org/Audiobook",
    "schema:license" : "https://creativecommons.org/publicdomain/zero/1.0/"
  },
  "links" : [ {
    "rel" : "self",
    "href" : "https://raw.githubusercontent.com/vietduyhuynh90s/book_storage_two1/main/EPUB/EPUB_6edd481c2ca872460c4b27b65fb383c8.json",
    "type" : "application/audiobook+json"
  }, {
    "rel" : "cover",
    "href" : "https://raw.githubusercontent.com/vietduyhuynh90s/book_storage_two1/main/IMAGE/IMAGE_6edd481c2ca872460c4b27b65fb383c8.jpg",
    "type" : "image/jpeg",
    "height" : 300,
    "width" : 300
  } ],
  "readingOrder" : [ {
    "href" : "https://archive.org/download/oan-hon-bi-phong-an/oan-hon-bi-phong-an.mp3",
    "type" : "audio/mpeg",
    "bitrate" : 128,
    "duration" : 3902,
    "title" : "oan-hon-bi-phong-an",
    "properties" : null,
    "alternate" : null
  } ],
  "toc" : [ {
    "href" : "https://archive.org/download/oan-hon-bi-phong-an/oan-hon-bi-phong-an.mp3",
    "title" : "oan-hon-bi-phong-an",
    "children" : [ ]
  } ],
  "@context" : "https://readium.org/webpub-manifest/context.jsonld"
}