{
  "metadata" : {
    "identifier" : "https://www.nettruyenio.com/truyen-tranh/lan-nua-toa-sang-495830",
    "title" : "Lần Nữa Toả Sáng - Chapter 52",
    "subtitle" : null,
    "author" : null,
    "narrator" : null,
    "language" : "vi",
    "description" : null,
    "publisher" : "N/A",
    "subject" : null,
    "modified" : null,
    "published" : "2023-07-02",
    "duration" : 0,
    "abridged" : false,
    "conformsTo" : "https://readium.org/webpub-manifest/profiles/divina",
    "numberOfPages" : 76,
    "readingProgression" : "ttb",
    "belongsTo" : null,
    "presentation" : {
      "fit" : "width",
      "overflow" : "scrolled",
      "continuous" : true
    },
    "@type" : null,
    "schema:license" : null
  },
  "links" : [ {
    "rel" : "self",
    "href" : "https://raw.githubusercontent.com/thuvienonline40/book_storage_collection/main/comic_manifest.json",
    "type" : "application/divina+json"
  } ],
  "readingOrder" : [ {
    "href" : "https://raw.githubusercontent.com/quetcccd/comic_storage1/main/IMAGE/IMAGE_37b8c6a69bbe631acadc3d53ffdf464a_97cfa768ab0661709af2f66997d6ec40_1efa062a8b207ef367b18d66ce9196d6.jpg",
    "type" : "image/jpeg",
    "bitrate" : 0,
    "duration" : 0,
    "title" : null,
    "properties" : null,
    "alternate" : [ {
      "href" : "https://i333.ntcdntempv3.com/data/images/49583/908675/001-4d54326.jpg?data=net",
      "type" : "image/jpeg",
      "bitrate" : 0,
      "duration" : 0,
      "title" : null,
      "properties" : null,
      "alternate" : null
    } ]
  }, {
    "href" : "https://raw.githubusercontent.com/quetcccd/comic_storage1/main/IMAGE/IMAGE_37b8c6a69bbe631acadc3d53ffdf464a_97cfa768ab0661709af2f66997d6ec40_7308dd48ed870388a2755f035e5ce01a.jpg",
    "type" : "image/jpeg",
    "bitrate" : 0,
    "duration" : 0,
    "title" : null,
    "properties" : null,
    "alternate" : [ {
      "href" : "https://i333.ntcdntempv3.com/data/images/49583/908675/002-db18dbc.jpg?data=net",
      "type" : "image/jpeg",
      "bitrate" : 0,
      "duration" : 0,
      "title" : null,
      "properties" : null,
      "alternate" : null
    } ]
  }, {
    "href" : "https://raw.githubusercontent.com/quetcccd/comic_storage1/main/IMAGE/IMAGE_37b8c6a69bbe631acadc3d53ffdf464a_97cfa768ab0661709af2f66997d6ec40_8333c8d33bbee496fde1d83c1a3f52ba.jpg",
    "type" : "image/jpeg",
    "bitrate" : 0,
    "duration" : 0,
    "title" : null,
    "properties" : null,
    "alternate" : [ {
      "href" : "https://i333.ntcdntempv3.com/data/images/49583/908675/003-69300a4.jpg?data=net",
      "type" : "image/jpeg",
      "bitrate" : 0,
      "duration" : 0,
      "title" : null,
      "properties" : null,
      "alternate" : null
    } ]
  }, {
    "href" : "https://raw.githubusercontent.com/quetcccd/comic_storage1/main/IMAGE/IMAGE_37b8c6a69bbe631acadc3d53ffdf464a_97cfa768ab0661709af2f66997d6ec40_e5b3e5dc09fe3094776ac24ae6fc4042.jpg",
    "type" : "image/jpeg",
    "bitrate" : 0,
    "duration" : 0,
    "title" : null,
    "properties" : null,
    "alternate" : [ {
      "href" : "https://i333.ntcdntempv3.com/data/images/49583/908675/004-3571b84.jpg?data=net",
      "type" : "image/jpeg",
      "bitrate" : 0,
      "duration" : 0,
      "title" : null,
      "properties" : null,
      "alternate" : null
    } ]
  }, {
    "href" : "https://raw.githubusercontent.com/quetcccd/comic_storage1/main/IMAGE/IMAGE_37b8c6a69bbe631acadc3d53ffdf464a_97cfa768ab0661709af2f66997d6ec40_8572739d9b09794cd5b57f05d2b18152.jpg",
    "type" : "image/jpeg",
    "bitrate" : 0,
    "duration" : 0,
    "title" : null,
    "properties" : null,
    "alternate" : [ {
      "href" : "https://i333.ntcdntempv3.com/data/images/49583/908675/005-ebf2565.jpg?data=net",
      "type" : "image/jpeg",
      "bitrate" : 0,
      "duration" : 0,
      "title" : null,
      "properties" : null,
      "alternate" : null
    } ]
  }, {
    "href" : "https://raw.githubusercontent.com/quetcccd/comic_storage1/main/IMAGE/IMAGE_37b8c6a69bbe631acadc3d53ffdf464a_97cfa768ab0661709af2f66997d6ec40_a2630c0b276d850d4d54a580b1f71cec.jpg",
    "type" : "image/jpeg",
    "bitrate" : 0,
    "duration" : 0,
    "title" : null,
    "properties" : null,
    "alternate" : [ {
      "href" : "https://i333.ntcdntempv3.com/data/images/49583/908675/006-04ce734.jpg?data=net",
      "type" : "image/jpeg",
      "bitrate" : 0,
      "duration" : 0,
      "title" : null,
      "properties" : null,
      "alternate" : null
    } ]
  }, {
    "href" : "https://raw.githubusercontent.com/quetcccd/comic_storage1/main/IMAGE/IMAGE_37b8c6a69bbe631acadc3d53ffdf464a_97cfa768ab0661709af2f66997d6ec40_ba93dfa68feecd9d73de338d7dccede2.jpg",
    "type" : "image/jpeg",
    "bitrate" : 0,
    "duration" : 0,
    "title" : null,
    "properties" : null,
    "alternate" : [ {
      "href" : "https://i333.ntcdntempv3.com/data/images/49583/908675/007-d3186a0.jpg?data=net",
      "type" : "image/jpeg",
      "bitrate" : 0,
      "duration" : 0,
      "title" : null,
      "properties" : null,
      "alternate" : null
    } ]
  }, {
    "href" : "https://raw.githubusercontent.com/quetcccd/comic_storage1/main/IMAGE/IMAGE_37b8c6a69bbe631acadc3d53ffdf464a_97cfa768ab0661709af2f66997d6ec40_b9a29b09e7689633bdfa4b785aba5a2e.jpg",
    "type" : "image/jpeg",
    "bitrate" : 0,
    "duration" : 0,
    "title" : null,
    "properties" : null,
    "alternate" : [ {
      "href" : "https://i333.ntcdntempv3.com/data/images/49583/908675/008-b22def6.jpg?data=net",
      "type" : "image/jpeg",
      "bitrate" : 0,
      "duration" : 0,
      "title" : null,
      "properties" : null,
      "alternate" : null
    } ]
  }, {
    "href" : "https://raw.githubusercontent.com/quetcccd/comic_storage1/main/IMAGE/IMAGE_37b8c6a69bbe631acadc3d53ffdf464a_97cfa768ab0661709af2f66997d6ec40_5d1735cc383b08633fc2a8c910424909.jpg",
    "type" : "image/jpeg",
    "bitrate" : 0,
    "duration" : 0,
    "title" : null,
    "properties" : null,
    "alternate" : [ {
      "href" : "https://i333.ntcdntempv3.com/data/images/49583/908675/009-a53ee63.jpg?data=net",
      "type" : "image/jpeg",
      "bitrate" : 0,
      "duration" : 0,
      "title" : null,
      "properties" : null,
      "alternate" : null
    } ]
  }, {
    "href" : "https://raw.githubusercontent.com/quetcccd/comic_storage1/main/IMAGE/IMAGE_37b8c6a69bbe631acadc3d53ffdf464a_97cfa768ab0661709af2f66997d6ec40_d30ccd001d9edc927adbaf282fd0cdc3.jpg",
    "type" : "image/jpeg",
    "bitrate" : 0,
    "duration" : 0,
    "title" : null,
    "properties" : null,
    "alternate" : [ {
      "href" : "https://i333.ntcdntempv3.com/data/images/49583/908675/010-66e2303.jpg?data=net",
      "type" : "image/jpeg",
      "bitrate" : 0,
      "duration" : 0,
      "title" : null,
      "properties" : null,
      "alternate" : null
    } ]
  }, {
    "href" : "https://raw.githubusercontent.com/quetcccd/comic_storage1/main/IMAGE/IMAGE_37b8c6a69bbe631acadc3d53ffdf464a_97cfa768ab0661709af2f66997d6ec40_61d0b1cecec0178f2ce337bbbe8b46d3.jpg",
    "type" : "image/jpeg",
    "bitrate" : 0,
    "duration" : 0,
    "title" : null,
    "properties" : null,
    "alternate" : [ {
      "href" : "https://i333.ntcdntempv3.com/data/images/49583/908675/011-717cc24.jpg?data=net",
      "type" : "image/jpeg",
      "bitrate" : 0,
      "duration" : 0,
      "title" : null,
      "properties" : null,
      "alternate" : null
    } ]
  }, {
    "href" : "https://raw.githubusercontent.com/quetcccd/comic_storage1/main/IMAGE/IMAGE_37b8c6a69bbe631acadc3d53ffdf464a_97cfa768ab0661709af2f66997d6ec40_4820c7d0d6efd614d1125a0059cb1d31.jpg",
    "type" : "image/jpeg",
    "bitrate" : 0,
    "duration" : 0,
    "title" : null,
    "properties" : null,
    "alternate" : [ {
      "href" : "https://i333.ntcdntempv3.com/data/images/49583/908675/012-577c4c7.jpg?data=net",
      "type" : "image/jpeg",
      "bitrate" : 0,
      "duration" : 0,
      "title" : null,
      "properties" : null,
      "alternate" : null
    } ]
  }, {
    "href" : "https://raw.githubusercontent.com/quetcccd/comic_storage1/main/IMAGE/IMAGE_37b8c6a69bbe631acadc3d53ffdf464a_97cfa768ab0661709af2f66997d6ec40_5f52f86d3447ce4b62716a9f7fc39290.jpg",
    "type" : "image/jpeg",
    "bitrate" : 0,
    "duration" : 0,
    "title" : null,
    "properties" : null,
    "alternate" : [ {
      "href" : "https://i333.ntcdntempv3.com/data/images/49583/908675/013-5e7e70f.jpg?data=net",
      "type" : "image/jpeg",
      "bitrate" : 0,
      "duration" : 0,
      "title" : null,
      "properties" : null,
      "alternate" : null
    } ]
  }, {
    "href" : "https://raw.githubusercontent.com/quetcccd/comic_storage1/main/IMAGE/IMAGE_37b8c6a69bbe631acadc3d53ffdf464a_97cfa768ab0661709af2f66997d6ec40_39e2f39f0d892132bb6c96ad4e1b6cc2.jpg",
    "type" : "image/jpeg",
    "bitrate" : 0,
    "duration" : 0,
    "title" : null,
    "properties" : null,
    "alternate" : [ {
      "href" : "https://i333.ntcdntempv3.com/data/images/49583/908675/014-62b7c3b.jpg?data=net",
      "type" : "image/jpeg",
      "bitrate" : 0,
      "duration" : 0,
      "title" : null,
      "properties" : null,
      "alternate" : null
    } ]
  }, {
    "href" : "https://raw.githubusercontent.com/quetcccd/comic_storage1/main/IMAGE/IMAGE_37b8c6a69bbe631acadc3d53ffdf464a_97cfa768ab0661709af2f66997d6ec40_4edc445d9a3ed1b2577818365300b836.jpg",
    "type" : "image/jpeg",
    "bitrate" : 0,
    "duration" : 0,
    "title" : null,
    "properties" : null,
    "alternate" : [ {
      "href" : "https://i333.ntcdntempv3.com/data/images/49583/908675/015-d552a5a.jpg?data=net",
      "type" : "image/jpeg",
      "bitrate" : 0,
      "duration" : 0,
      "title" : null,
      "properties" : null,
      "alternate" : null
    } ]
  }, {
    "href" : "https://raw.githubusercontent.com/quetcccd/comic_storage1/main/IMAGE/IMAGE_37b8c6a69bbe631acadc3d53ffdf464a_97cfa768ab0661709af2f66997d6ec40_2585b335122517df3e16f57784bf47f9.jpg",
    "type" : "image/jpeg",
    "bitrate" : 0,
    "duration" : 0,
    "title" : null,
    "properties" : null,
    "alternate" : [ {
      "href" : "https://i333.ntcdntempv3.com/data/images/49583/908675/016-ee8d7cd.jpg?data=net",
      "type" : "image/jpeg",
      "bitrate" : 0,
      "duration" : 0,
      "title" : null,
      "properties" : null,
      "alternate" : null
    } ]
  }, {
    "href" : "https://raw.githubusercontent.com/quetcccd/comic_storage1/main/IMAGE/IMAGE_37b8c6a69bbe631acadc3d53ffdf464a_97cfa768ab0661709af2f66997d6ec40_465650d22146312aca64aecc34287b88.jpg",
    "type" : "image/jpeg",
    "bitrate" : 0,
    "duration" : 0,
    "title" : null,
    "properties" : null,
    "alternate" : [ {
      "href" : "https://i333.ntcdntempv3.com/data/images/49583/908675/017-3202931.jpg?data=net",
      "type" : "image/jpeg",
      "bitrate" : 0,
      "duration" : 0,
      "title" : null,
      "properties" : null,
      "alternate" : null
    } ]
  }, {
    "href" : "https://raw.githubusercontent.com/quetcccd/comic_storage1/main/IMAGE/IMAGE_37b8c6a69bbe631acadc3d53ffdf464a_97cfa768ab0661709af2f66997d6ec40_a2747b4c0a20e17eb7ac4f2c4c182ed2.jpg",
    "type" : "image/jpeg",
    "bitrate" : 0,
    "duration" : 0,
    "title" : null,
    "properties" : null,
    "alternate" : [ {
      "href" : "https://i333.ntcdntempv3.com/data/images/49583/908675/018-7f226a7.jpg?data=net",
      "type" : "image/jpeg",
      "bitrate" : 0,
      "duration" : 0,
      "title" : null,
      "properties" : null,
      "alternate" : null
    } ]
  }, {
    "href" : "https://raw.githubusercontent.com/quetcccd/comic_storage1/main/IMAGE/IMAGE_37b8c6a69bbe631acadc3d53ffdf464a_97cfa768ab0661709af2f66997d6ec40_2344c2cca3811720c15b089a04b6b5f5.jpg",
    "type" : "image/jpeg",
    "bitrate" : 0,
    "duration" : 0,
    "title" : null,
    "properties" : null,
    "alternate" : [ {
      "href" : "https://i333.ntcdntempv3.com/data/images/49583/908675/019-6e1d604.jpg?data=net",
      "type" : "image/jpeg",
      "bitrate" : 0,
      "duration" : 0,
      "title" : null,
      "properties" : null,
      "alternate" : null
    } ]
  }, {
    "href" : "https://raw.githubusercontent.com/quetcccd/comic_storage1/main/IMAGE/IMAGE_37b8c6a69bbe631acadc3d53ffdf464a_97cfa768ab0661709af2f66997d6ec40_37f1bcbac0a716c01500e563ffe73d73.jpg",
    "type" : "image/jpeg",
    "bitrate" : 0,
    "duration" : 0,
    "title" : null,
    "properties" : null,
    "alternate" : [ {
      "href" : "https://i333.ntcdntempv3.com/data/images/49583/908675/020-1328f34.jpg?data=net",
      "type" : "image/jpeg",
      "bitrate" : 0,
      "duration" : 0,
      "title" : null,
      "properties" : null,
      "alternate" : null
    } ]
  }, {
    "href" : "https://raw.githubusercontent.com/quetcccd/comic_storage1/main/IMAGE/IMAGE_37b8c6a69bbe631acadc3d53ffdf464a_97cfa768ab0661709af2f66997d6ec40_aeed3e1e1ef7add087198a4ba792454f.jpg",
    "type" : "image/jpeg",
    "bitrate" : 0,
    "duration" : 0,
    "title" : null,
    "properties" : null,
    "alternate" : [ {
      "href" : "https://i333.ntcdntempv3.com/data/images/49583/908675/021-4696b88.jpg?data=net",
      "type" : "image/jpeg",
      "bitrate" : 0,
      "duration" : 0,
      "title" : null,
      "properties" : null,
      "alternate" : null
    } ]
  }, {
    "href" : "https://raw.githubusercontent.com/quetcccd/comic_storage1/main/IMAGE/IMAGE_37b8c6a69bbe631acadc3d53ffdf464a_97cfa768ab0661709af2f66997d6ec40_df8b9cbb3350f6731a26acfa054490c0.jpg",
    "type" : "image/jpeg",
    "bitrate" : 0,
    "duration" : 0,
    "title" : null,
    "properties" : null,
    "alternate" : [ {
      "href" : "https://i333.ntcdntempv3.com/data/images/49583/908675/022-a8e66a1.jpg?data=net",
      "type" : "image/jpeg",
      "bitrate" : 0,
      "duration" : 0,
      "title" : null,
      "properties" : null,
      "alternate" : null
    } ]
  }, {
    "href" : "https://raw.githubusercontent.com/quetcccd/comic_storage1/main/IMAGE/IMAGE_37b8c6a69bbe631acadc3d53ffdf464a_97cfa768ab0661709af2f66997d6ec40_9b30088e689d3e844f2ad80f978b1cb3.jpg",
    "type" : "image/jpeg",
    "bitrate" : 0,
    "duration" : 0,
    "title" : null,
    "properties" : null,
    "alternate" : [ {
      "href" : "https://i333.ntcdntempv3.com/data/images/49583/908675/023-6d08059.jpg?data=net",
      "type" : "image/jpeg",
      "bitrate" : 0,
      "duration" : 0,
      "title" : null,
      "properties" : null,
      "alternate" : null
    } ]
  }, {
    "href" : "https://raw.githubusercontent.com/quetcccd/comic_storage1/main/IMAGE/IMAGE_37b8c6a69bbe631acadc3d53ffdf464a_97cfa768ab0661709af2f66997d6ec40_2cc07f2a68344d3465edc7d7e51f045c.jpg",
    "type" : "image/jpeg",
    "bitrate" : 0,
    "duration" : 0,
    "title" : null,
    "properties" : null,
    "alternate" : [ {
      "href" : "https://i333.ntcdntempv3.com/data/images/49583/908675/024-e598a68.jpg?data=net",
      "type" : "image/jpeg",
      "bitrate" : 0,
      "duration" : 0,
      "title" : null,
      "properties" : null,
      "alternate" : null
    } ]
  }, {
    "href" : "https://raw.githubusercontent.com/quetcccd/comic_storage1/main/IMAGE/IMAGE_37b8c6a69bbe631acadc3d53ffdf464a_97cfa768ab0661709af2f66997d6ec40_8e5a62d588e8a82489d8ac8a311bb620.jpg",
    "type" : "image/jpeg",
    "bitrate" : 0,
    "duration" : 0,
    "title" : null,
    "properties" : null,
    "alternate" : [ {
      "href" : "https://i333.ntcdntempv3.com/data/images/49583/908675/025-27dfd4c.jpg?data=net",
      "type" : "image/jpeg",
      "bitrate" : 0,
      "duration" : 0,
      "title" : null,
      "properties" : null,
      "alternate" : null
    } ]
  }, {
    "href" : "https://raw.githubusercontent.com/quetcccd/comic_storage1/main/IMAGE/IMAGE_37b8c6a69bbe631acadc3d53ffdf464a_97cfa768ab0661709af2f66997d6ec40_b35dc0d8cee378f861de2b720aa6dc57.jpg",
    "type" : "image/jpeg",
    "bitrate" : 0,
    "duration" : 0,
    "title" : null,
    "properties" : null,
    "alternate" : [ {
      "href" : "https://i333.ntcdntempv3.com/data/images/49583/908675/026-3029616.jpg?data=net",
      "type" : "image/jpeg",
      "bitrate" : 0,
      "duration" : 0,
      "title" : null,
      "properties" : null,
      "alternate" : null
    } ]
  }, {
    "href" : "https://raw.githubusercontent.com/quetcccd/comic_storage1/main/IMAGE/IMAGE_37b8c6a69bbe631acadc3d53ffdf464a_97cfa768ab0661709af2f66997d6ec40_f42c1d69d2b49f561479c6ccf633e7b4.jpg",
    "type" : "image/jpeg",
    "bitrate" : 0,
    "duration" : 0,
    "title" : null,
    "properties" : null,
    "alternate" : [ {
      "href" : "https://i333.ntcdntempv3.com/data/images/49583/908675/027-e76e30f.jpg?data=net",
      "type" : "image/jpeg",
      "bitrate" : 0,
      "duration" : 0,
      "title" : null,
      "properties" : null,
      "alternate" : null
    } ]
  }, {
    "href" : "https://raw.githubusercontent.com/quetcccd/comic_storage1/main/IMAGE/IMAGE_37b8c6a69bbe631acadc3d53ffdf464a_97cfa768ab0661709af2f66997d6ec40_183998ef6a5539b87c03e172087934a4.jpg",
    "type" : "image/jpeg",
    "bitrate" : 0,
    "duration" : 0,
    "title" : null,
    "properties" : null,
    "alternate" : [ {
      "href" : "https://i333.ntcdntempv3.com/data/images/49583/908675/028-4412c1b.jpg?data=net",
      "type" : "image/jpeg",
      "bitrate" : 0,
      "duration" : 0,
      "title" : null,
      "properties" : null,
      "alternate" : null
    } ]
  }, {
    "href" : "https://raw.githubusercontent.com/quetcccd/comic_storage1/main/IMAGE/IMAGE_37b8c6a69bbe631acadc3d53ffdf464a_97cfa768ab0661709af2f66997d6ec40_93c0b7855ec384762fd2b4f0f5dc5421.jpg",
    "type" : "image/jpeg",
    "bitrate" : 0,
    "duration" : 0,
    "title" : null,
    "properties" : null,
    "alternate" : [ {
      "href" : "https://i333.ntcdntempv3.com/data/images/49583/908675/029-8a0d729.jpg?data=net",
      "type" : "image/jpeg",
      "bitrate" : 0,
      "duration" : 0,
      "title" : null,
      "properties" : null,
      "alternate" : null
    } ]
  }, {
    "href" : "https://raw.githubusercontent.com/quetcccd/comic_storage1/main/IMAGE/IMAGE_37b8c6a69bbe631acadc3d53ffdf464a_97cfa768ab0661709af2f66997d6ec40_fb6330514937ca1d27d96f9528a645d7.jpg",
    "type" : "image/jpeg",
    "bitrate" : 0,
    "duration" : 0,
    "title" : null,
    "properties" : null,
    "alternate" : [ {
      "href" : "https://i333.ntcdntempv3.com/data/images/49583/908675/030-b3fb2f3.jpg?data=net",
      "type" : "image/jpeg",
      "bitrate" : 0,
      "duration" : 0,
      "title" : null,
      "properties" : null,
      "alternate" : null
    } ]
  }, {
    "href" : "https://raw.githubusercontent.com/quetcccd/comic_storage1/main/IMAGE/IMAGE_37b8c6a69bbe631acadc3d53ffdf464a_97cfa768ab0661709af2f66997d6ec40_71103dee60e502bbf7ca5dac8ea18a02.jpg",
    "type" : "image/jpeg",
    "bitrate" : 0,
    "duration" : 0,
    "title" : null,
    "properties" : null,
    "alternate" : [ {
      "href" : "https://i333.ntcdntempv3.com/data/images/49583/908675/031-dab2e49.jpg?data=net",
      "type" : "image/jpeg",
      "bitrate" : 0,
      "duration" : 0,
      "title" : null,
      "properties" : null,
      "alternate" : null
    } ]
  }, {
    "href" : "https://raw.githubusercontent.com/quetcccd/comic_storage1/main/IMAGE/IMAGE_37b8c6a69bbe631acadc3d53ffdf464a_97cfa768ab0661709af2f66997d6ec40_506cd2868ab025c549297caaef6454cd.jpg",
    "type" : "image/jpeg",
    "bitrate" : 0,
    "duration" : 0,
    "title" : null,
    "properties" : null,
    "alternate" : [ {
      "href" : "https://i333.ntcdntempv3.com/data/images/49583/908675/032-d978e7a.jpg?data=net",
      "type" : "image/jpeg",
      "bitrate" : 0,
      "duration" : 0,
      "title" : null,
      "properties" : null,
      "alternate" : null
    } ]
  }, {
    "href" : "https://raw.githubusercontent.com/quetcccd/comic_storage1/main/IMAGE/IMAGE_37b8c6a69bbe631acadc3d53ffdf464a_97cfa768ab0661709af2f66997d6ec40_d049fd654bc45b0a8f78e2bd778be1e2.jpg",
    "type" : "image/jpeg",
    "bitrate" : 0,
    "duration" : 0,
    "title" : null,
    "properties" : null,
    "alternate" : [ {
      "href" : "https://i333.ntcdntempv3.com/data/images/49583/908675/033-7769eb4.jpg?data=net",
      "type" : "image/jpeg",
      "bitrate" : 0,
      "duration" : 0,
      "title" : null,
      "properties" : null,
      "alternate" : null
    } ]
  }, {
    "href" : "https://raw.githubusercontent.com/quetcccd/comic_storage1/main/IMAGE/IMAGE_37b8c6a69bbe631acadc3d53ffdf464a_97cfa768ab0661709af2f66997d6ec40_d76e9e542f39ea91a347db30b64fe432.jpg",
    "type" : "image/jpeg",
    "bitrate" : 0,
    "duration" : 0,
    "title" : null,
    "properties" : null,
    "alternate" : [ {
      "href" : "https://i333.ntcdntempv3.com/data/images/49583/908675/034-ef26f9f.jpg?data=net",
      "type" : "image/jpeg",
      "bitrate" : 0,
      "duration" : 0,
      "title" : null,
      "properties" : null,
      "alternate" : null
    } ]
  }, {
    "href" : "https://raw.githubusercontent.com/quetcccd/comic_storage1/main/IMAGE/IMAGE_37b8c6a69bbe631acadc3d53ffdf464a_97cfa768ab0661709af2f66997d6ec40_36fff6c0ad676def0cd88e6e1fb38daf.jpg",
    "type" : "image/jpeg",
    "bitrate" : 0,
    "duration" : 0,
    "title" : null,
    "properties" : null,
    "alternate" : [ {
      "href" : "https://i333.ntcdntempv3.com/data/images/49583/908675/035-137839e.jpg?data=net",
      "type" : "image/jpeg",
      "bitrate" : 0,
      "duration" : 0,
      "title" : null,
      "properties" : null,
      "alternate" : null
    } ]
  }, {
    "href" : "https://raw.githubusercontent.com/quetcccd/comic_storage1/main/IMAGE/IMAGE_37b8c6a69bbe631acadc3d53ffdf464a_97cfa768ab0661709af2f66997d6ec40_5d2ed0fdb1c3070cecf27903b267cb58.jpg",
    "type" : "image/jpeg",
    "bitrate" : 0,
    "duration" : 0,
    "title" : null,
    "properties" : null,
    "alternate" : [ {
      "href" : "https://i333.ntcdntempv3.com/data/images/49583/908675/036-7c13005.jpg?data=net",
      "type" : "image/jpeg",
      "bitrate" : 0,
      "duration" : 0,
      "title" : null,
      "properties" : null,
      "alternate" : null
    } ]
  }, {
    "href" : "https://raw.githubusercontent.com/quetcccd/comic_storage1/main/IMAGE/IMAGE_37b8c6a69bbe631acadc3d53ffdf464a_97cfa768ab0661709af2f66997d6ec40_d759a84465b2a4d7d0ce324344210d7e.jpg",
    "type" : "image/jpeg",
    "bitrate" : 0,
    "duration" : 0,
    "title" : null,
    "properties" : null,
    "alternate" : [ {
      "href" : "https://i333.ntcdntempv3.com/data/images/49583/908675/037-c33c67d.jpg?data=net",
      "type" : "image/jpeg",
      "bitrate" : 0,
      "duration" : 0,
      "title" : null,
      "properties" : null,
      "alternate" : null
    } ]
  }, {
    "href" : "https://raw.githubusercontent.com/quetcccd/comic_storage1/main/IMAGE/IMAGE_37b8c6a69bbe631acadc3d53ffdf464a_97cfa768ab0661709af2f66997d6ec40_401d36d6fd7e5306f334728dfa6bfccd.jpg",
    "type" : "image/jpeg",
    "bitrate" : 0,
    "duration" : 0,
    "title" : null,
    "properties" : null,
    "alternate" : [ {
      "href" : "https://i333.ntcdntempv3.com/data/images/49583/908675/038-8875ab4.jpg?data=net",
      "type" : "image/jpeg",
      "bitrate" : 0,
      "duration" : 0,
      "title" : null,
      "properties" : null,
      "alternate" : null
    } ]
  }, {
    "href" : "https://raw.githubusercontent.com/quetcccd/comic_storage1/main/IMAGE/IMAGE_37b8c6a69bbe631acadc3d53ffdf464a_97cfa768ab0661709af2f66997d6ec40_c95d8ab7d7dfa1bbc84f4397725a9283.jpg",
    "type" : "image/jpeg",
    "bitrate" : 0,
    "duration" : 0,
    "title" : null,
    "properties" : null,
    "alternate" : [ {
      "href" : "https://i333.ntcdntempv3.com/data/images/49583/908675/039-f8ac0e0.jpg?data=net",
      "type" : "image/jpeg",
      "bitrate" : 0,
      "duration" : 0,
      "title" : null,
      "properties" : null,
      "alternate" : null
    } ]
  }, {
    "href" : "https://raw.githubusercontent.com/quetcccd/comic_storage1/main/IMAGE/IMAGE_37b8c6a69bbe631acadc3d53ffdf464a_97cfa768ab0661709af2f66997d6ec40_fb5a53e74a7a27130f3520917555736f.jpg",
    "type" : "image/jpeg",
    "bitrate" : 0,
    "duration" : 0,
    "title" : null,
    "properties" : null,
    "alternate" : [ {
      "href" : "https://i333.ntcdntempv3.com/data/images/49583/908675/040-c128a06.jpg?data=net",
      "type" : "image/jpeg",
      "bitrate" : 0,
      "duration" : 0,
      "title" : null,
      "properties" : null,
      "alternate" : null
    } ]
  }, {
    "href" : "https://raw.githubusercontent.com/quetcccd/comic_storage1/main/IMAGE/IMAGE_37b8c6a69bbe631acadc3d53ffdf464a_97cfa768ab0661709af2f66997d6ec40_bb7c1107a61d4b00ddf4c0acb47d8e1f.jpg",
    "type" : "image/jpeg",
    "bitrate" : 0,
    "duration" : 0,
    "title" : null,
    "properties" : null,
    "alternate" : [ {
      "href" : "https://i333.ntcdntempv3.com/data/images/49583/908675/041-731699e.jpg?data=net",
      "type" : "image/jpeg",
      "bitrate" : 0,
      "duration" : 0,
      "title" : null,
      "properties" : null,
      "alternate" : null
    } ]
  }, {
    "href" : "https://raw.githubusercontent.com/quetcccd/comic_storage1/main/IMAGE/IMAGE_37b8c6a69bbe631acadc3d53ffdf464a_97cfa768ab0661709af2f66997d6ec40_6f52ab7c0770f578b8272824bc8682f7.jpg",
    "type" : "image/jpeg",
    "bitrate" : 0,
    "duration" : 0,
    "title" : null,
    "properties" : null,
    "alternate" : [ {
      "href" : "https://i333.ntcdntempv3.com/data/images/49583/908675/042-b2c2f70.jpg?data=net",
      "type" : "image/jpeg",
      "bitrate" : 0,
      "duration" : 0,
      "title" : null,
      "properties" : null,
      "alternate" : null
    } ]
  }, {
    "href" : "https://raw.githubusercontent.com/quetcccd/comic_storage1/main/IMAGE/IMAGE_37b8c6a69bbe631acadc3d53ffdf464a_97cfa768ab0661709af2f66997d6ec40_5bdc10612eb41ebff7bfc701aa8381ad.jpg",
    "type" : "image/jpeg",
    "bitrate" : 0,
    "duration" : 0,
    "title" : null,
    "properties" : null,
    "alternate" : [ {
      "href" : "https://i333.ntcdntempv3.com/data/images/49583/908675/043-2ccdfae.jpg?data=net",
      "type" : "image/jpeg",
      "bitrate" : 0,
      "duration" : 0,
      "title" : null,
      "properties" : null,
      "alternate" : null
    } ]
  }, {
    "href" : "https://raw.githubusercontent.com/quetcccd/comic_storage1/main/IMAGE/IMAGE_37b8c6a69bbe631acadc3d53ffdf464a_97cfa768ab0661709af2f66997d6ec40_cb40b49048b40481f545bd3425f69594.jpg",
    "type" : "image/jpeg",
    "bitrate" : 0,
    "duration" : 0,
    "title" : null,
    "properties" : null,
    "alternate" : [ {
      "href" : "https://i333.ntcdntempv3.com/data/images/49583/908675/044-0543baa.jpg?data=net",
      "type" : "image/jpeg",
      "bitrate" : 0,
      "duration" : 0,
      "title" : null,
      "properties" : null,
      "alternate" : null
    } ]
  }, {
    "href" : "https://raw.githubusercontent.com/quetcccd/comic_storage1/main/IMAGE/IMAGE_37b8c6a69bbe631acadc3d53ffdf464a_97cfa768ab0661709af2f66997d6ec40_14b0a103f41cd741c1fcf80a5e883108.jpg",
    "type" : "image/jpeg",
    "bitrate" : 0,
    "duration" : 0,
    "title" : null,
    "properties" : null,
    "alternate" : [ {
      "href" : "https://i333.ntcdntempv3.com/data/images/49583/908675/045-491da13.jpg?data=net",
      "type" : "image/jpeg",
      "bitrate" : 0,
      "duration" : 0,
      "title" : null,
      "properties" : null,
      "alternate" : null
    } ]
  }, {
    "href" : "https://raw.githubusercontent.com/quetcccd/comic_storage1/main/IMAGE/IMAGE_37b8c6a69bbe631acadc3d53ffdf464a_97cfa768ab0661709af2f66997d6ec40_f6515d58839d9af488edc3a95d8deeb2.jpg",
    "type" : "image/jpeg",
    "bitrate" : 0,
    "duration" : 0,
    "title" : null,
    "properties" : null,
    "alternate" : [ {
      "href" : "https://i333.ntcdntempv3.com/data/images/49583/908675/046-358c704.jpg?data=net",
      "type" : "image/jpeg",
      "bitrate" : 0,
      "duration" : 0,
      "title" : null,
      "properties" : null,
      "alternate" : null
    } ]
  }, {
    "href" : "https://raw.githubusercontent.com/quetcccd/comic_storage1/main/IMAGE/IMAGE_37b8c6a69bbe631acadc3d53ffdf464a_97cfa768ab0661709af2f66997d6ec40_0fed0df29e735e74a39fd662ba968556.jpg",
    "type" : "image/jpeg",
    "bitrate" : 0,
    "duration" : 0,
    "title" : null,
    "properties" : null,
    "alternate" : [ {
      "href" : "https://i333.ntcdntempv3.com/data/images/49583/908675/047-1e5ee82.jpg?data=net",
      "type" : "image/jpeg",
      "bitrate" : 0,
      "duration" : 0,
      "title" : null,
      "properties" : null,
      "alternate" : null
    } ]
  }, {
    "href" : "https://raw.githubusercontent.com/quetcccd/comic_storage1/main/IMAGE/IMAGE_37b8c6a69bbe631acadc3d53ffdf464a_97cfa768ab0661709af2f66997d6ec40_cec76cd754519a0d5d6e9ae58a9649d4.jpg",
    "type" : "image/jpeg",
    "bitrate" : 0,
    "duration" : 0,
    "title" : null,
    "properties" : null,
    "alternate" : [ {
      "href" : "https://i333.ntcdntempv3.com/data/images/49583/908675/048-a0b414d.jpg?data=net",
      "type" : "image/jpeg",
      "bitrate" : 0,
      "duration" : 0,
      "title" : null,
      "properties" : null,
      "alternate" : null
    } ]
  }, {
    "href" : "https://raw.githubusercontent.com/quetcccd/comic_storage1/main/IMAGE/IMAGE_37b8c6a69bbe631acadc3d53ffdf464a_97cfa768ab0661709af2f66997d6ec40_0fd2c706da06e2b98ca5ae4bb5bcef3a.jpg",
    "type" : "image/jpeg",
    "bitrate" : 0,
    "duration" : 0,
    "title" : null,
    "properties" : null,
    "alternate" : [ {
      "href" : "https://i333.ntcdntempv3.com/data/images/49583/908675/049-0a22d9d.jpg?data=net",
      "type" : "image/jpeg",
      "bitrate" : 0,
      "duration" : 0,
      "title" : null,
      "properties" : null,
      "alternate" : null
    } ]
  }, {
    "href" : "https://raw.githubusercontent.com/quetcccd/comic_storage1/main/IMAGE/IMAGE_37b8c6a69bbe631acadc3d53ffdf464a_97cfa768ab0661709af2f66997d6ec40_8f9b36f627824269879a29239a64fc60.jpg",
    "type" : "image/jpeg",
    "bitrate" : 0,
    "duration" : 0,
    "title" : null,
    "properties" : null,
    "alternate" : [ {
      "href" : "https://i333.ntcdntempv3.com/data/images/49583/908675/050-e3d4ba4.jpg?data=net",
      "type" : "image/jpeg",
      "bitrate" : 0,
      "duration" : 0,
      "title" : null,
      "properties" : null,
      "alternate" : null
    } ]
  }, {
    "href" : "https://raw.githubusercontent.com/quetcccd/comic_storage1/main/IMAGE/IMAGE_37b8c6a69bbe631acadc3d53ffdf464a_97cfa768ab0661709af2f66997d6ec40_e7e3254935990655f9b1beb10e36cf85.jpg",
    "type" : "image/jpeg",
    "bitrate" : 0,
    "duration" : 0,
    "title" : null,
    "properties" : null,
    "alternate" : [ {
      "href" : "https://i333.ntcdntempv3.com/data/images/49583/908675/051-d8b56ae.jpg?data=net",
      "type" : "image/jpeg",
      "bitrate" : 0,
      "duration" : 0,
      "title" : null,
      "properties" : null,
      "alternate" : null
    } ]
  }, {
    "href" : "https://raw.githubusercontent.com/quetcccd/comic_storage1/main/IMAGE/IMAGE_37b8c6a69bbe631acadc3d53ffdf464a_97cfa768ab0661709af2f66997d6ec40_1ccfebb38b4ef0fbaa57c88d12e0648f.jpg",
    "type" : "image/jpeg",
    "bitrate" : 0,
    "duration" : 0,
    "title" : null,
    "properties" : null,
    "alternate" : [ {
      "href" : "https://i333.ntcdntempv3.com/data/images/49583/908675/052-1cecbe3.jpg?data=net",
      "type" : "image/jpeg",
      "bitrate" : 0,
      "duration" : 0,
      "title" : null,
      "properties" : null,
      "alternate" : null
    } ]
  }, {
    "href" : "https://raw.githubusercontent.com/quetcccd/comic_storage1/main/IMAGE/IMAGE_37b8c6a69bbe631acadc3d53ffdf464a_97cfa768ab0661709af2f66997d6ec40_2aa19eeba8494634075193b660aa9ecb.jpg",
    "type" : "image/jpeg",
    "bitrate" : 0,
    "duration" : 0,
    "title" : null,
    "properties" : null,
    "alternate" : [ {
      "href" : "https://i333.ntcdntempv3.com/data/images/49583/908675/053-c7dec13.jpg?data=net",
      "type" : "image/jpeg",
      "bitrate" : 0,
      "duration" : 0,
      "title" : null,
      "properties" : null,
      "alternate" : null
    } ]
  }, {
    "href" : "https://raw.githubusercontent.com/quetcccd/comic_storage1/main/IMAGE/IMAGE_37b8c6a69bbe631acadc3d53ffdf464a_97cfa768ab0661709af2f66997d6ec40_7feb37916f27e3791b9f731b0bfd3a63.jpg",
    "type" : "image/jpeg",
    "bitrate" : 0,
    "duration" : 0,
    "title" : null,
    "properties" : null,
    "alternate" : [ {
      "href" : "https://i333.ntcdntempv3.com/data/images/49583/908675/054-2e5b13d.jpg?data=net",
      "type" : "image/jpeg",
      "bitrate" : 0,
      "duration" : 0,
      "title" : null,
      "properties" : null,
      "alternate" : null
    } ]
  }, {
    "href" : "https://raw.githubusercontent.com/quetcccd/comic_storage1/main/IMAGE/IMAGE_37b8c6a69bbe631acadc3d53ffdf464a_97cfa768ab0661709af2f66997d6ec40_cc5328783acfe9f6a8cb3f1378331351.jpg",
    "type" : "image/jpeg",
    "bitrate" : 0,
    "duration" : 0,
    "title" : null,
    "properties" : null,
    "alternate" : [ {
      "href" : "https://i333.ntcdntempv3.com/data/images/49583/908675/055-65e72a9.jpg?data=net",
      "type" : "image/jpeg",
      "bitrate" : 0,
      "duration" : 0,
      "title" : null,
      "properties" : null,
      "alternate" : null
    } ]
  }, {
    "href" : "https://raw.githubusercontent.com/quetcccd/comic_storage1/main/IMAGE/IMAGE_37b8c6a69bbe631acadc3d53ffdf464a_97cfa768ab0661709af2f66997d6ec40_e453177fe9429cda2197f3c773158b48.jpg",
    "type" : "image/jpeg",
    "bitrate" : 0,
    "duration" : 0,
    "title" : null,
    "properties" : null,
    "alternate" : [ {
      "href" : "https://i333.ntcdntempv3.com/data/images/49583/908675/056-6a21b68.jpg?data=net",
      "type" : "image/jpeg",
      "bitrate" : 0,
      "duration" : 0,
      "title" : null,
      "properties" : null,
      "alternate" : null
    } ]
  }, {
    "href" : "https://raw.githubusercontent.com/quetcccd/comic_storage1/main/IMAGE/IMAGE_37b8c6a69bbe631acadc3d53ffdf464a_97cfa768ab0661709af2f66997d6ec40_3856e377644116d8c683f71983ee7f88.jpg",
    "type" : "image/jpeg",
    "bitrate" : 0,
    "duration" : 0,
    "title" : null,
    "properties" : null,
    "alternate" : [ {
      "href" : "https://i333.ntcdntempv3.com/data/images/49583/908675/057-d622094.jpg?data=net",
      "type" : "image/jpeg",
      "bitrate" : 0,
      "duration" : 0,
      "title" : null,
      "properties" : null,
      "alternate" : null
    } ]
  } ],
  "toc" : null,
  "@context" : "https://readium.org/webpub-manifest/context.jsonld"
}